[
  {
    "Name": "7z.exe",
    "Size": "1.32 MB",
    "ModTime": "2024-05-10T23:34:52.304528300Z",
    "Source": "https://bin.ajam.dev/x64_Windows/7z.exe",
    "B3SUM": null,
    "SHA256": null,
    "Repo": null
  },
  {
    "Name": "BLAKE3SUM.txt",
    "Size": "13.12 kB",
    "ModTime": "2024-05-10T23:38:03.979255500Z",
    "Source": "https://bin.ajam.dev/x64_Windows/BLAKE3SUM.txt",
    "B3SUM": null,
    "SHA256": null,
    "Repo": null
  },
  {
    "Name": "BUILD.log.txt",
    "Size": "925.18 kB",
    "ModTime": "2024-05-10T23:40:47.306952800Z",
    "Source": "https://bin.ajam.dev/x64_Windows/BUILD.log.txt",
    "B3SUM": null,
    "SHA256": null,
    "Repo": null
  },
  {
    "Name": "FILE.txt",
    "Size": "18.84 kB",
    "ModTime": "2024-05-05T23:40:04.287866000Z",
    "Source": "https://bin.ajam.dev/x64_Windows/FILE.txt",
    "B3SUM": null,
    "SHA256": null,
    "Repo": null
  },
  {
    "Name": "METADATA.json",
    "Size": "61.78 kB",
    "ModTime": "2024-05-12T00:18:45.869231734Z",
    "Source": "https://bin.ajam.dev/x64_Windows/METADATA.json",
    "B3SUM": null,
    "SHA256": null,
    "Repo": null
  },
  {
    "Name": "SHA256SUM.txt",
    "Size": "13.12 kB",
    "ModTime": "2024-05-10T23:38:10.437743900Z",
    "Source": "https://bin.ajam.dev/x64_Windows/SHA256SUM.txt",
    "B3SUM": null,
    "SHA256": null,
    "Repo": null
  },
  {
    "Name": "SIZE.txt",
    "Size": "4861 B",
    "ModTime": "2024-05-10T23:38:02.266494200Z",
    "Source": "https://bin.ajam.dev/x64_Windows/SIZE.txt",
    "B3SUM": null,
    "SHA256": null,
    "Repo": null
  },
  {
    "Name": "_toolpack_x64_Windows.7z",
    "Size": "282.84 MB",
    "ModTime": "2024-05-10T23:40:34.786701600Z",
    "Source": "https://bin.ajam.dev/x64_Windows/_toolpack_x64_Windows.7z",
    "B3SUM": null,
    "SHA256": null,
    "Repo": null
  },
  {
    "Name": "_toolpack_x64_Windows_BLAKE3SUM.txt",
    "Size": "93 B",
    "ModTime": "2024-05-10T23:40:43.347612400Z",
    "Source": "https://bin.ajam.dev/x64_Windows/_toolpack_x64_Windows_BLAKE3SUM.txt",
    "B3SUM": null,
    "SHA256": null,
    "Repo": null
  },
  {
    "Name": "_toolpack_x64_Windows_SHA256SUM.txt",
    "Size": "95 B",
    "ModTime": "2024-05-10T23:40:45.445149900Z",
    "Source": "https://bin.ajam.dev/x64_Windows/_toolpack_x64_Windows_SHA256SUM.txt",
    "B3SUM": null,
    "SHA256": null,
    "Repo": null
  },
  {
    "Name": "actionlint.exe",
    "Size": "5.41 MB",
    "ModTime": "2024-05-10T23:34:53.039389600Z",
    "Source": "https://bin.ajam.dev/x64_Windows/actionlint.exe",
    "B3SUM": "6ee0bb0070ec7d935eb8501949fc0f066cd4af1e364a717c739638a86ebac1d1",
    "SHA256": "ab2dbfcc05215a164f2fa839f30a61c4816f823618193413d8a5907819dee285",
    "Repo": "https://github.com/rhysd/actionlint"
  },
  {
    "Name": "age.exe",
    "Size": "3.88 MB",
    "ModTime": "2024-05-10T23:34:54.024475100Z",
    "Source": "https://bin.ajam.dev/x64_Windows/age.exe",
    "B3SUM": "6a849155a61ef1ede4d6b5335ff8c253aca039339a0ee21334525fdf27e64376",
    "SHA256": "aa6a9c8df7666e088124563bff0b4da0467f82caa4cfa22bca9b9fe7a71ab407",
    "Repo": "https://github.com/FiloSottile/age"
  },
  {
    "Name": "algernon.exe",
    "Size": "26.77 MB",
    "ModTime": "2024-05-10T23:34:55.321941700Z",
    "Source": "https://bin.ajam.dev/x64_Windows/algernon.exe",
    "B3SUM": "73fc74bb3f5f707b5339c20c6433a030ca28777323dd2abd5cf6e8835e7829a3",
    "SHA256": "c16883abb642eb70567838bc6f9680cc372971d1cd24ef62e0cdd3d310c6a6a8",
    "Repo": "https://github.com/xyproto/algernon"
  },
  {
    "Name": "alist.exe",
    "Size": "66.83 MB",
    "ModTime": "2024-05-10T23:34:56.916029900Z",
    "Source": "https://bin.ajam.dev/x64_Windows/alist.exe",
    "B3SUM": "aa0643b48a810d6a1e025a07b3f84933c72456e59bf6c884c4a8a5d70092c4cb",
    "SHA256": "85ba449bc6e7e0d14ca927aa5e19f2dfa52ea243b0b0f1e5a311ae499ff48299",
    "Repo": "https://github.com/alist-org/alist"
  },
  {
    "Name": "anew-rs.exe",
    "Size": "786.94 kB",
    "ModTime": "2024-05-10T23:34:57.979085300Z",
    "Source": "https://bin.ajam.dev/x64_Windows/anew-rs.exe",
    "B3SUM": "355133507dddd103da2dc33ef6e4b1943f5c7efacae3ba7ad9890640f1af4011",
    "SHA256": "ad48e7bb9e1981c72b19853799312b3d984c82f6078649892161810e3d30666c",
    "Repo": "https://github.com/zer0yu/anew"
  },
  {
    "Name": "anew.exe",
    "Size": "786.94 kB",
    "ModTime": "2024-05-10T23:34:58.987740300Z",
    "Source": "https://bin.ajam.dev/x64_Windows/anew.exe",
    "B3SUM": "58968ab871a222ec54843b02a3c049eaba0e99c0c834a40db7bd1317be551ccb",
    "SHA256": "79ef94ce9a43e912638cd2ab444c6747371b20b0df33475cf2cfc5b1fcc4e807",
    "Repo": "https://github.com/zer0yu/anew"
  },
  {
    "Name": "arch.exe",
    "Size": "826.37 kB",
    "ModTime": "2024-05-10T23:34:59.980209800Z",
    "Source": "https://bin.ajam.dev/x64_Windows/arch.exe",
    "B3SUM": "19128f0a4c5ea157b43b5be4107a31b09a90936a85876f6e8983c4f603737dba",
    "SHA256": "d686f9879dbd9746cb542844b64d5e35f275a9a4ea546e8898d584d367849d9c",
    "Repo": "https://github.com/uutils/coreutils"
  },
  {
    "Name": "b3sum.exe",
    "Size": "1.06 MB",
    "ModTime": "2024-05-10T23:35:00.980391600Z",
    "Source": "https://bin.ajam.dev/x64_Windows/b3sum.exe",
    "B3SUM": "2e916351d2b28c06d65987a4cf25ca64569701e73860b77430fe7ed9d23e829b",
    "SHA256": "8ca4a0ba7d7d7173c17fc2b2ba07be9d49d8de78d93f0681ede398b2fb638aef",
    "Repo": "https://github.com/BLAKE3-team/BLAKE3"
  },
  {
    "Name": "base32.exe",
    "Size": "944.13 kB",
    "ModTime": "2024-05-10T23:35:01.980756100Z",
    "Source": "https://bin.ajam.dev/x64_Windows/base32.exe",
    "B3SUM": "e5e88e1a6e1efa23f80f1c19eb9cc4ef1f746ebe472e550462cef389c0f2f536",
    "SHA256": "034029c414a8a17570a13fa4edbf16c0bb969588f6c7c3156e5af8d38b46121f",
    "Repo": "https://github.com/uutils/coreutils"
  },
  {
    "Name": "base64.exe",
    "Size": "944.64 kB",
    "ModTime": "2024-05-10T23:35:02.980953200Z",
    "Source": "https://bin.ajam.dev/x64_Windows/base64.exe",
    "B3SUM": "540b0bc46412bee9fdf26bffef6c55f1d6da8cf1bd4d9b75571b740868fa4836",
    "SHA256": "3c86b1fe6658f8b30c0fb7fd833c1997c2bd4ad2cd5f46789bd368a2595991b8",
    "Repo": "https://github.com/uutils/coreutils"
  },
  {
    "Name": "basename.exe",
    "Size": "840.19 kB",
    "ModTime": "2024-05-10T23:35:03.981326500Z",
    "Source": "https://bin.ajam.dev/x64_Windows/basename.exe",
    "B3SUM": "fa080ab22a0518589d746ef826b9bc520af00b4388d2080682e0cd071a3fba28",
    "SHA256": "0373900dce68be455d92c182ca61ab3c2cd43a5ddfdd44fbd8d13ae9600f0fe7",
    "Repo": "https://github.com/uutils/coreutils"
  },
  {
    "Name": "basenc.exe",
    "Size": "968.7 kB",
    "ModTime": "2024-05-10T23:35:04.997064400Z",
    "Source": "https://bin.ajam.dev/x64_Windows/basenc.exe",
    "B3SUM": "89707f6ad232fb7396c4b678124348812fd4609e0b69331de7d454024d9ef234",
    "SHA256": "0ab00c5c6765e8d1af9e2921f629deec8619de9bc5eae1509c9c433d30c34d4f",
    "Repo": "https://github.com/uutils/coreutils"
  },
  {
    "Name": "bat.exe",
    "Size": "6.32 MB",
    "ModTime": "2024-05-10T23:35:06.075544800Z",
    "Source": "https://bin.ajam.dev/x64_Windows/bat.exe",
    "B3SUM": "3cbe0225d18e5431533ecf1b96ab0039b27888c28149b463eb5b69193f474aa8",
    "SHA256": "083b642c98ddd28995b425096f0c423b852563cafee85add4711a8303c602991",
    "Repo": "https://github.com/sharkdp/bat"
  },
  {
    "Name": "batcat.exe",
    "Size": "6.32 MB",
    "ModTime": "2024-05-10T23:35:07.075652100Z",
    "Source": "https://bin.ajam.dev/x64_Windows/batcat.exe",
    "B3SUM": "cd1aec31daf733a1e2da7b18cfdf898d2e2030a9551d4c63ee5d06ac63c0c6c8",
    "SHA256": "016757490a3bac1666b004817461c64f1c697a80cfdd6ab25562099e94305b88",
    "Repo": "https://github.com/sharkdp/bat"
  },
  {
    "Name": "botsay.exe",
    "Size": "1.7 MB",
    "ModTime": "2024-05-10T23:35:08.014386300Z",
    "Source": "https://bin.ajam.dev/x64_Windows/botsay.exe",
    "B3SUM": "7c203b53ece3381f84919efec47605bb7d008183a416ee99ec28b1ea935d9c17",
    "SHA256": "38c352b2d6056002591f8e023f1edd3102fd09e7ecbdf2663f6b9251458b75cc",
    "Repo": "https://github.com/xyproto/botsay"
  },
  {
    "Name": "brook_windows_amd64.exe",
    "Size": "20.63 MB",
    "ModTime": "2024-05-11T18:00:15.387227700Z",
    "Source": "https://bin.ajam.dev/x64_Windows/brook_windows_amd64.exe",
    "B3SUM": null,
    "SHA256": null,
    "Repo": null
  },
  {
    "Name": "brutespray.exe",
    "Size": "25.75 MB",
    "ModTime": "2024-05-10T23:35:09.367336500Z",
    "Source": "https://bin.ajam.dev/x64_Windows/brutespray.exe",
    "B3SUM": "51347c3e7ff7322ac979687bba145bb317240a995cc7b2408aa321da07be72d7",
    "SHA256": "b9be39bfd434104053617f0dc0a888745ed11f95e179ea0546b5f340258abbd9",
    "Repo": "https://github.com/x90skysn3k/brutespray"
  },
  {
    "Name": "busybox-unicode.exe",
    "Size": "666.11 kB",
    "ModTime": "2024-05-10T23:35:10.010881600Z",
    "Source": "https://bin.ajam.dev/x64_Windows/busybox-unicode.exe",
    "B3SUM": null,
    "SHA256": null,
    "Repo": null
  },
  {
    "Name": "busybox.exe",
    "Size": "659.97 kB",
    "ModTime": "2024-05-10T23:35:11.012734000Z",
    "Source": "https://bin.ajam.dev/x64_Windows/busybox.exe",
    "B3SUM": null,
    "SHA256": null,
    "Repo": null
  },
  {
    "Name": "cat.exe",
    "Size": "861.7 kB",
    "ModTime": "2024-05-10T23:35:12.013078600Z",
    "Source": "https://bin.ajam.dev/x64_Windows/cat.exe",
    "B3SUM": "46b152d9d4023ba4da7a393dee19835383d8c299c561849d0da2a2e5acb904f3",
    "SHA256": "8556752b695330f5db7bc850134cf872daf4b8b779c50a3c422a4766987d3d3f",
    "Repo": "https://github.com/uutils/coreutils"
  },
  {
    "Name": "certstream.exe",
    "Size": "4.86 MB",
    "ModTime": "2024-04-27T10:42:09.656277800Z",
    "Source": "https://bin.ajam.dev/x64_Windows/certstream.exe",
    "B3SUM": null,
    "SHA256": null,
    "Repo": null
  },
  {
    "Name": "cheat.exe",
    "Size": "11.57 MB",
    "ModTime": "2024-05-10T23:35:13.162317100Z",
    "Source": "https://bin.ajam.dev/x64_Windows/cheat.exe",
    "B3SUM": "42d772aa7de60b438962de98dcf4afe4f036100efe06ff7bd2ba748d2a6b3b27",
    "SHA256": "26ad7507b19f6c61205a5b22f380f37d9c1e8055cbb750f944ffec9310f7b5a2",
    "Repo": "https://github.com/cheat/cheat"
  },
  {
    "Name": "cksum.exe",
    "Size": "1.03 MB",
    "ModTime": "2024-05-10T23:35:14.022379100Z",
    "Source": "https://bin.ajam.dev/x64_Windows/cksum.exe",
    "B3SUM": "661209b1032b89534909f0fd0e59577180d414b2b8ee8f919e30dcf8e4330eb0",
    "SHA256": "ae65348ce244fd07d2015672e47013c3c1873d1929c8162932c29315ee2bd20d",
    "Repo": "https://github.com/uutils/coreutils"
  },
  {
    "Name": "cloudflared.exe",
    "Size": "26.46 MB",
    "ModTime": "2024-05-10T23:35:15.366459200Z",
    "Source": "https://bin.ajam.dev/x64_Windows/cloudflared.exe",
    "B3SUM": "269b78b983f38bdf37ec8d0126d28cc445e74cb8d8ebae6399ce157f9e4af53b",
    "SHA256": "a9a12956deeb1150ede3cf38bde86b94a419007df180ab934858654da31711a6",
    "Repo": "https://github.com/cloudflare/cloudflared"
  },
  {
    "Name": "comm.exe",
    "Size": "842.75 kB",
    "ModTime": "2024-05-10T23:35:16.022904300Z",
    "Source": "https://bin.ajam.dev/x64_Windows/comm.exe",
    "B3SUM": "e758e260d386b21c782f79dda8e99f2959e48a35a0c32a8472b3d222eb995eb8",
    "SHA256": "4c379edf425439bcef249b8150af7e0ac0160933627ecb6340d318a85726c159",
    "Repo": "https://github.com/uutils/coreutils"
  },
  {
    "Name": "coreutils-rs.exe",
    "Size": "9.62 MB",
    "ModTime": "2024-05-10T23:35:17.132821300Z",
    "Source": "https://bin.ajam.dev/x64_Windows/coreutils-rs.exe",
    "B3SUM": "74a0df380b7a3e6993be91ba89baafd68e9eb804579d62ed31dc74fdc49c6a3e",
    "SHA256": "be9fd2ef09532020644f0a0c16cf1d950646bd21171cbbd97d78f6b439072efa",
    "Repo": "https://github.com/uutils/coreutils"
  },
  {
    "Name": "coreutils.exe",
    "Size": "9.62 MB",
    "ModTime": "2024-05-10T23:35:18.133252200Z",
    "Source": "https://bin.ajam.dev/x64_Windows/coreutils.exe",
    "B3SUM": "8ea595ba1af9d2f2610e0d02c4af380d10185dd24f56b3aa2d8563806afc09f9",
    "SHA256": "729e08597bd1463d7f1ff03a7dea58c45a886ed665e6f0f80d80e398bcdf26b1",
    "Repo": "https://github.com/uutils/coreutils"
  },
  {
    "Name": "cp.exe",
    "Size": "1.29 MB",
    "ModTime": "2024-05-10T23:35:19.024148200Z",
    "Source": "https://bin.ajam.dev/x64_Windows/cp.exe",
    "B3SUM": "e6b31d50c3cefcdaef23a2e5295f25742885a17e62b6c9bc56097635ea16c765",
    "SHA256": "963e654f8aa0389193f8938c097e65b0d10b4580296e677176d82ed4af3ef9c1",
    "Repo": "https://github.com/uutils/coreutils"
  },
  {
    "Name": "croc.exe",
    "Size": "8.63 MB",
    "ModTime": "2024-05-10T23:35:20.134082100Z",
    "Source": "https://bin.ajam.dev/x64_Windows/croc.exe",
    "B3SUM": "9a54df4375b040008e1c186bec43f7dcdc94c36a7c3d214c5a3045dff9c6b67c",
    "SHA256": "9b78d1551bde2b993a7f13b9c9357c18e098207d537a05da068382b12e0ee6f4",
    "Repo": "https://github.com/schollz/croc"
  },
  {
    "Name": "csplit.exe",
    "Size": "2.32 MB",
    "ModTime": "2024-05-10T23:35:21.056771600Z",
    "Source": "https://bin.ajam.dev/x64_Windows/csplit.exe",
    "B3SUM": "947c62b6c96983cd0c6bb7bebce87bcf27164c85030563bd2d91c55085daf441",
    "SHA256": "684ae243613843ffe95bc365d4151a2fb1873cf1a8876afcc5b5acaf6a6bfeae",
    "Repo": "https://github.com/uutils/coreutils"
  },
  {
    "Name": "curl.exe",
    "Size": "7.46 MB",
    "ModTime": "2024-05-10T23:35:22.103987900Z",
    "Source": "https://bin.ajam.dev/x64_Windows/curl.exe",
    "B3SUM": "235325b9ee47c559fc938ea20ab2dd9c56f67840d140f278ea5cf428905f1dee",
    "SHA256": "392a7ed07eabb56c926610eecc3ff0cb397cc696b7738f20a7a1e9797d5dadcc",
    "Repo": "https://github.com/stunnel/static-curl"
  },
  {
    "Name": "cut.exe",
    "Size": "910.34 kB",
    "ModTime": "2024-05-10T23:35:23.026447200Z",
    "Source": "https://bin.ajam.dev/x64_Windows/cut.exe",
    "B3SUM": "9db4e9838f7332a2624fa3d1cc0cb4c3ca3f38cd4629af2970df76fc07d1e0e6",
    "SHA256": "a6f9c19de0d11f5d48e903446d5d061f7b0c2193751f842605bd903e91f2ab69",
    "Repo": "https://github.com/uutils/coreutils"
  },
  {
    "Name": "cutlines.exe",
    "Size": "1.96 MB",
    "ModTime": "2024-05-10T23:35:24.042351100Z",
    "Source": "https://bin.ajam.dev/x64_Windows/cutlines.exe",
    "B3SUM": "8c4dbe244512c01f3db9eee01eb51831ebc1e58721728efcc695af8be46c8ff2",
    "SHA256": "1231d0971f8736803c48515dc3dbaf6b8c806af6ff00a6590f9166da86d9097b",
    "Repo": "hhttps://github.com/Azathothas/Arsenal"
  },
  {
    "Name": "date.exe",
    "Size": "2.38 MB",
    "ModTime": "2024-05-10T23:35:25.058258800Z",
    "Source": "https://bin.ajam.dev/x64_Windows/date.exe",
    "B3SUM": "3a1daef615aeea2f5bf991a90bfaf5375b563fea986df51901a3ff54a2f3a1ab",
    "SHA256": "ab9691921e03b683773477c336746241fef1bed2e48c50ffac0eb245d3032629",
    "Repo": "https://github.com/uutils/coreutils"
  },
  {
    "Name": "dd.exe",
    "Size": "1.02 MB",
    "ModTime": "2024-05-10T23:35:26.027427700Z",
    "Source": "https://bin.ajam.dev/x64_Windows/dd.exe",
    "B3SUM": "87d58501d5b0f79e072a10bb90c37733fa4d89e3feb28d745560d315c77ff437",
    "SHA256": "a3fc3b413ce131e781109bc090f82843e1f42d9d5befcecdd38103d561f6374e",
    "Repo": "https://github.com/uutils/coreutils"
  },
  {
    "Name": "deprun.exe",
    "Size": "3.06 MB",
    "ModTime": "2024-05-10T23:35:27.058958000Z",
    "Source": "https://bin.ajam.dev/x64_Windows/deprun.exe",
    "B3SUM": "b93e744334425acf82e5a2de48962ca2d9b1766bf7528b4b53aebdbca5b0fc40",
    "SHA256": "33e49a9a19246a77139dae4f086e99ff2b70a85fe0e3098755b3be98ff196cd2",
    "Repo": "https://github.com/marcoesposito1988/dependency_runner"
  },
  {
    "Name": "df.exe",
    "Size": "962.56 kB",
    "ModTime": "2024-05-10T23:35:28.028442000Z",
    "Source": "https://bin.ajam.dev/x64_Windows/df.exe",
    "B3SUM": "3c9c69d3dd4e868aa779a0c31e26354f3a91b54dd875a612e2e9b83636fdb24a",
    "SHA256": "43c8831d5812a0dfb28f3974a568fa5fbf7445cf390ade0b58a2a07bbcfbb696",
    "Repo": "https://github.com/uutils/coreutils"
  },
  {
    "Name": "dir.exe",
    "Size": "1.25 MB",
    "ModTime": "2024-05-10T23:35:29.028769400Z",
    "Source": "https://bin.ajam.dev/x64_Windows/dir.exe",
    "B3SUM": "a192fb7c9deafee6d694a7ee8bf16926b85da3e31c7b406e96a338c881dde04e",
    "SHA256": "7ba2a000cdd06d2139b8da83adc5e85c05163959f3312899436933c62b26a98a",
    "Repo": "https://github.com/uutils/coreutils"
  },
  {
    "Name": "dircolors.exe",
    "Size": "901.12 kB",
    "ModTime": "2024-05-10T23:35:30.032969900Z",
    "Source": "https://bin.ajam.dev/x64_Windows/dircolors.exe",
    "B3SUM": "0cfd4a159de3501213580a61d16257c82ac49042a4b9bfd62ccbf4557b651202",
    "SHA256": "afc5be00b4ee350b9b410b4fe7eb2560e51fc2184b270813dc978ce5004a4762",
    "Repo": "https://github.com/uutils/coreutils"
  },
  {
    "Name": "dirname.exe",
    "Size": "816.64 kB",
    "ModTime": "2024-05-10T23:35:31.033589600Z",
    "Source": "https://bin.ajam.dev/x64_Windows/dirname.exe",
    "B3SUM": "ad509b2e6e23acf67cb850561cc93e9ba50096ba1b905be3d17f3da074bc84e1",
    "SHA256": "4ec64fbaa1ab35249ccafe8fb3e651d4cbb44f0310342f0b7c5bff8adead53ef",
    "Repo": "https://github.com/uutils/coreutils"
  },
  {
    "Name": "du.exe",
    "Size": "1.12 MB",
    "ModTime": "2024-05-10T23:35:32.034044700Z",
    "Source": "https://bin.ajam.dev/x64_Windows/du.exe",
    "B3SUM": "a4cf3e59ad7579454c3a4b6752130445c14657035d7cb16e61ab9dfcf42b7075",
    "SHA256": "8e0e94a78de81b5c1089cd8d9d2209178224285b5a476642637656d5366e6dca",
    "Repo": "https://github.com/uutils/coreutils"
  },
  {
    "Name": "dua.exe",
    "Size": "1.56 MB",
    "ModTime": "2024-05-10T23:35:33.050146300Z",
    "Source": "https://bin.ajam.dev/x64_Windows/dua.exe",
    "B3SUM": "8969ffa02d0b8951743275d9d07e47be54b48b48f8d03d19bb48c6eb66e65c11",
    "SHA256": "30d9a0bc700dd47516e54d8832fdc7198e4cc14da12cc84103b9f10d7f868ad0",
    "Repo": "https://github.com/Byron/dua-cli"
  },
  {
    "Name": "dufs.exe",
    "Size": "3.68 MB",
    "ModTime": "2024-05-10T23:35:34.081713600Z",
    "Source": "https://bin.ajam.dev/x64_Windows/dufs.exe",
    "B3SUM": "5e3d5045d756d0e95125a12a99a752f90f970f37440069cf8ef29c492a2233bc",
    "SHA256": "a6341bec5d51a4b256b642dd2b19aff8c76b9eb94f1110aced2bf5df8050621b",
    "Repo": "https://github.com/sigoden/dufs"
  },
  {
    "Name": "dust.exe",
    "Size": "2.79 MB",
    "ModTime": "2024-05-10T23:35:35.066216000Z",
    "Source": "https://bin.ajam.dev/x64_Windows/dust.exe",
    "B3SUM": "13ee6d9dd63db2e2f2fa446d7ff79075286fc6ffb6211194f3c01e89ac562469",
    "SHA256": "7c139cd5b7a583c490393d5d06e140175470c1398e79cf80721c6215c4809e99",
    "Repo": "https://github.com/bootandy/dust"
  },
  {
    "Name": "echo.exe",
    "Size": "815.1 kB",
    "ModTime": "2024-05-10T23:35:36.035466100Z",
    "Source": "https://bin.ajam.dev/x64_Windows/echo.exe",
    "B3SUM": "9377e736ab7788f2b92231b956bd3914d64864e5cce33851db49827224ca2304",
    "SHA256": "bf96f65a7e9c5b556151a7bd4fb6fe617aba13418b6de0e8a3997351154e1551",
    "Repo": "https://github.com/uutils/coreutils"
  },
  {
    "Name": "eget.exe",
    "Size": "6.94 MB",
    "ModTime": "2024-05-10T23:35:37.113864500Z",
    "Source": "https://bin.ajam.dev/x64_Windows/eget.exe",
    "B3SUM": "9f1c5b53e1526d8e8eb0135e33e8210ae9fc13b185efd5f104b8435db2da68ba",
    "SHA256": "fe4698bbfb29d0d9dabfdffffb0c985f96920b3d9178008e6d402c4486ad8236",
    "Repo": "https://github.com/zyedidia/eget"
  },
  {
    "Name": "ein.exe",
    "Size": "9.17 MB",
    "ModTime": "2024-05-10T23:35:38.145799000Z",
    "Source": "https://bin.ajam.dev/x64_Windows/ein.exe",
    "B3SUM": null,
    "SHA256": null,
    "Repo": null
  },
  {
    "Name": "env.exe",
    "Size": "1.02 MB",
    "ModTime": "2024-05-10T23:35:39.036948400Z",
    "Source": "https://bin.ajam.dev/x64_Windows/env.exe",
    "B3SUM": "c84bf583131bc90338854d89e1cfb7b9ea6e6a29d3b1284edfe4fb45dbaef5a1",
    "SHA256": "4d32b3048d99543d6e0cc40358fcc25a4834b8b87a5ea34e4e4a8e66bed12da2",
    "Repo": "https://github.com/uutils/coreutils"
  },
  {
    "Name": "err.exe",
    "Size": "2.29 MB",
    "ModTime": "2024-05-10T23:35:40.069314700Z",
    "Source": "https://bin.ajam.dev/x64_Windows/err.exe",
    "B3SUM": "092196c69000ebabf5a1db513ef58439216cbb388d46ec41d88acb7db9f7507a",
    "SHA256": "3dacd545b25bd65e2d2a5612695e6b5b50b8315d022bd9c9e7f7e48c6a45c829",
    "Repo": "https://www.microsoft.com/en-us/download/details.aspx?id=100432"
  },
  {
    "Name": "expand.exe",
    "Size": "872.96 kB",
    "ModTime": "2024-05-10T23:35:41.048871300Z",
    "Source": "https://bin.ajam.dev/x64_Windows/expand.exe",
    "B3SUM": "fe9c3efcb87cbb6118b648ec1f59e20c0c24b5c5a366724970b69ad2abc1d503",
    "SHA256": "245e03a640d6b0c077c93857bd3f385f80301c2a936bc87254f0b5e23bbaa82f",
    "Repo": "https://github.com/uutils/coreutils"
  },
  {
    "Name": "expr.exe",
    "Size": "1.43 MB",
    "ModTime": "2024-05-10T23:35:42.040067100Z",
    "Source": "https://bin.ajam.dev/x64_Windows/expr.exe",
    "B3SUM": "459010b3ec29f3254b0c6387be121f58ad66fdd87f62b15af6d22f2b9f024e59",
    "SHA256": "20fa1015d935694ef771b5e28df0c8c9f3304ac54360c99a28dc17c2aaf837db",
    "Repo": "https://github.com/uutils/coreutils"
  },
  {
    "Name": "factor.exe",
    "Size": "1.23 MB",
    "ModTime": "2024-05-10T23:35:43.055879700Z",
    "Source": "https://bin.ajam.dev/x64_Windows/factor.exe",
    "B3SUM": "19169d3d4e49fa5fa7fb6aca712c83db7348fc2794fd1a7576e59fd426e07511",
    "SHA256": "d468e2b4d93f0a1a39cb85ca05695c9c78b1f277a8d95e1079e49cec78a7c880",
    "Repo": "https://github.com/uutils/coreutils"
  },
  {
    "Name": "false.exe",
    "Size": "758.27 kB",
    "ModTime": "2024-05-10T23:35:44.040648300Z",
    "Source": "https://bin.ajam.dev/x64_Windows/false.exe",
    "B3SUM": "f12d1c30995efef44e5d981ef3259e5f43f3e26ba42ab94932d861835a5b3805",
    "SHA256": "22012cbd1fea3fca17caf4cbfef00bb47dfd230f52240d53a8ac147ae009c805",
    "Repo": "https://github.com/uutils/coreutils"
  },
  {
    "Name": "fastfetch.exe",
    "Size": "1.33 MB",
    "ModTime": "2024-05-10T23:35:45.040930000Z",
    "Source": "https://bin.ajam.dev/x64_Windows/fastfetch.exe",
    "B3SUM": "98516788b05b0e9248b228dfb21f923f356c387fbc8b4174c7dcfbf46458aaee",
    "SHA256": "25599012cdc161fec2906b5a831c72bdd874ba7b7153f09a175dfba90632a49e",
    "Repo": "https://github.com/fastfetch-cli/fastfetch"
  },
  {
    "Name": "ffmpeg.exe",
    "Size": "140.49 MB",
    "ModTime": "2024-05-10T23:35:48.120327900Z",
    "Source": "https://bin.ajam.dev/x64_Windows/ffmpeg.exe",
    "B3SUM": "85577ea65a33ffc0222f6315600c100423b3087083376ee45091c6f83fb1d62c",
    "SHA256": "290794a83233de7afce5c3b8c488a177f7752837fb6446aa39ed7b9080c57890",
    "Repo": "https://ffmpeg.org"
  },
  {
    "Name": "ffplay.exe",
    "Size": "140.31 MB",
    "ModTime": "2024-05-10T23:35:51.105965500Z",
    "Source": "https://bin.ajam.dev/x64_Windows/ffplay.exe",
    "B3SUM": null,
    "SHA256": null,
    "Repo": null
  },
  {
    "Name": "ffprobe.exe",
    "Size": "140.32 MB",
    "ModTime": "2024-05-10T23:35:54.154038100Z",
    "Source": "https://bin.ajam.dev/x64_Windows/ffprobe.exe",
    "B3SUM": "a7f45078d1d5745cd91e2b76ff38a6f246fe051e23ab996cad6025daa7e19d89",
    "SHA256": "b57e8448f05068134ad569358a612ddb5cc62a59eac8a925e7288692a6dc5958",
    "Repo": "https://ffmpeg.org"
  },
  {
    "Name": "find-rs.exe",
    "Size": "2.13 MB",
    "ModTime": "2024-05-10T23:35:55.076480300Z",
    "Source": "https://bin.ajam.dev/x64_Windows/find-rs.exe",
    "B3SUM": "5d2ba9e8fee5cfb6ff1eb4342dacbe336ce1658a705aefe4e64f8d10b59c591e",
    "SHA256": "1797e03ceacd0f22bbfdffc45477a3c492d4e9ab4765815365034faa9528cb61",
    "Repo": "https://github.com/uutils/findutils"
  },
  {
    "Name": "find.exe",
    "Size": "2.13 MB",
    "ModTime": "2024-05-10T23:35:56.061229000Z",
    "Source": "https://bin.ajam.dev/x64_Windows/find.exe",
    "B3SUM": "5fa44e1cf1e4731cca62127247389f080d824e2ec7050962e6be41f394c68e42",
    "SHA256": "bf3d62e590ff8be1ffd41cc5280f9184ce3933d06b5888df90f64fca5e5c6732",
    "Repo": "https://github.com/uutils/findutils"
  },
  {
    "Name": "flashfetch.exe",
    "Size": "1.18 MB",
    "ModTime": "2024-05-10T23:35:57.045879200Z",
    "Source": "https://bin.ajam.dev/x64_Windows/flashfetch.exe",
    "B3SUM": "e4ff7bd7839d4c5ebdb8be05bf70bd5abbf5b1b57177583b2ab83f2e2ccf7898",
    "SHA256": "f24465e0aacb2cd316ace92ae3cdfc9cc7af1da229b7ac1bae32332a4db011e2",
    "Repo": "https://github.com/fastfetch-cli/fastfetch"
  },
  {
    "Name": "fmt.exe",
    "Size": "903.68 kB",
    "ModTime": "2024-05-10T23:35:58.046881100Z",
    "Source": "https://bin.ajam.dev/x64_Windows/fmt.exe",
    "B3SUM": "88789db4fa5f79eb8ecf1c1ab921a051c49d7384c756e35569213977914bf3bc",
    "SHA256": "8cbe4919eeda25226a6ef881b3e5d0e66289e8b57962e8a779aaf5ebed4c217f",
    "Repo": "https://github.com/uutils/coreutils"
  },
  {
    "Name": "fold.exe",
    "Size": "859.65 kB",
    "ModTime": "2024-05-10T23:35:59.062814400Z",
    "Source": "https://bin.ajam.dev/x64_Windows/fold.exe",
    "B3SUM": "9645e9b4d7be8a3880896432797e7e2db5fc4594014ecda66cc00e7c7b660aa7",
    "SHA256": "dd2341f570ca8eb7b6c34ec7b0bc1091fadde80c3fc36846f5d1e7c51742375f",
    "Repo": "https://github.com/uutils/coreutils"
  },
  {
    "Name": "gdu.exe",
    "Size": "14.23 MB",
    "ModTime": "2024-05-10T23:36:00.238405500Z",
    "Source": "https://bin.ajam.dev/x64_Windows/gdu.exe",
    "B3SUM": "452883153fc0bc55ec1835bb31a3439ad3f25e87d43a3cbf2d22fb1dc372338b",
    "SHA256": "409087d8410e9d6cb46939fc981377387d3b4efe915463a8bad9417632b46c2b",
    "Repo": "https://github.com/dundee/gdu"
  },
  {
    "Name": "geodns.exe",
    "Size": "2.37 MB",
    "ModTime": "2024-05-10T23:36:01.098311600Z",
    "Source": "https://bin.ajam.dev/x64_Windows/geodns.exe",
    "B3SUM": "4e2185d13e93c73eed3a712efdb38eeb5eb7379665389fd6deebd9e3c5fac4cf",
    "SHA256": "7cec16aa694cc51cc60aef5bdcd8f7b4a10e02de74b54de4d810113dc40fc887",
    "Repo": "https://gitlab.com/shodan-public/geonet-rs"
  },
  {
    "Name": "geoping.exe",
    "Size": "2.37 MB",
    "ModTime": "2024-05-10T23:36:02.098741800Z",
    "Source": "https://bin.ajam.dev/x64_Windows/geoping.exe",
    "B3SUM": "4f93eb8ecb3ffb2b15a895204d2c6d085d548d871da83685bb5cb21a35a37b94",
    "SHA256": "acf556922e8adef471b6b5174d11c3bacf39f7fa0ac27f4e74c4552e707f19e6",
    "Repo": "https://gitlab.com/shodan-public/geonet-rs"
  },
  {
    "Name": "gix.exe",
    "Size": "18.42 MB",
    "ModTime": "2024-05-10T23:36:03.302089700Z",
    "Source": "https://bin.ajam.dev/x64_Windows/gix.exe",
    "B3SUM": null,
    "SHA256": null,
    "Repo": null
  },
  {
    "Name": "hashsum.exe",
    "Size": "2.48 MB",
    "ModTime": "2024-05-10T23:36:04.083977100Z",
    "Source": "https://bin.ajam.dev/x64_Windows/hashsum.exe",
    "B3SUM": "9fdd95c66875449db82f9a54eaa193805701762abb97be53bbb2e369b49af5b9",
    "SHA256": "547bc076899c6f9d80bd3853f4c8c2a29fc9f5862c23150b4d81e5d5c26b9683",
    "Repo": "https://github.com/uutils/coreutils"
  },
  {
    "Name": "head.exe",
    "Size": "899.07 kB",
    "ModTime": "2024-05-10T23:36:05.068533200Z",
    "Source": "https://bin.ajam.dev/x64_Windows/head.exe",
    "B3SUM": "af67612bfffc7aa40f3ebcd267a24e787ed88c113d4ff1d1d79d953bccbe2755",
    "SHA256": "bcbef84faf4771b072047a3033f03f9aebabf257f575ea88921bf31bd0f67a4b",
    "Repo": "https://github.com/uutils/coreutils"
  },
  {
    "Name": "hostname.exe",
    "Size": "844.29 kB",
    "ModTime": "2024-05-10T23:36:06.068899200Z",
    "Source": "https://bin.ajam.dev/x64_Windows/hostname.exe",
    "B3SUM": "ae93899119a354e6d645a7fdf6f9f4ed1da926cf24ebb7d12bff2e3b2406d21b",
    "SHA256": "f112bfd9a585d5852aaf1e852950645cf5dc06faa50ffb60be9989e8d37b1b32",
    "Repo": "https://github.com/uutils/coreutils"
  },
  {
    "Name": "hyperfine.exe",
    "Size": "1.33 MB",
    "ModTime": "2024-05-10T23:36:07.084675800Z",
    "Source": "https://bin.ajam.dev/x64_Windows/hyperfine.exe",
    "B3SUM": "1c85baf33d97ad91120e9265302fe7150c0c0cf60b5e16e91a4141a360171f54",
    "SHA256": "c6f5b2cd89f89c0c887c64718cb79d530d9a97223b57ce72afa677677ee000c2",
    "Repo": "https://github.com/sharkdp/hyperfine"
  },
  {
    "Name": "inscope.exe",
    "Size": "1.8 MB",
    "ModTime": "2024-05-10T23:36:08.101072500Z",
    "Source": "https://bin.ajam.dev/x64_Windows/inscope.exe",
    "B3SUM": "405226182db1f5fdbd9c690075ff58678ebff03440bb48c163deaea83611800a",
    "SHA256": "2336809d941395e9c0a2394e6f384548c01a73ba70426c1677ae0734596f563c",
    "Repo": "hhttps://github.com/Azathothas/Arsenal"
  },
  {
    "Name": "iperf3.exe",
    "Size": "141.31 kB",
    "ModTime": "2024-05-10T23:36:09.069983600Z",
    "Source": "https://bin.ajam.dev/x64_Windows/iperf3.exe",
    "B3SUM": "07bc764b03104a230b17574aba79c953fffb2bd96016bf3e0f8d5ae55b49eef7",
    "SHA256": "55b693dbb7613c90f6bf40527c75167b5e47fa435149543bd4ac8835c68c3811",
    "Repo": "https://github.com/userdocs/iperf3-static\nhttps://github.com/userdocs/iperf3-static"
  },
  {
    "Name": "join.exe",
    "Size": "913.92 kB",
    "ModTime": "2024-05-10T23:36:10.086517100Z",
    "Source": "https://bin.ajam.dev/x64_Windows/join.exe",
    "B3SUM": "ea007a1d967b0ea790a0e677eaed875d37af5328d8a39478dd2ed8b05c3b2128",
    "SHA256": "dbf590a6c907821d8d7a61e5b44409614239f2efedc2cf7f57a9d6440bcf9a66",
    "Repo": "https://github.com/uutils/coreutils"
  },
  {
    "Name": "jq.exe",
    "Size": "985.09 kB",
    "ModTime": "2024-05-10T23:36:11.094933700Z",
    "Source": "https://bin.ajam.dev/x64_Windows/jq.exe",
    "B3SUM": "14ecfc958ddf77abcfbe2f692fc4fca6b1e6718de64125095ac054168849a98d",
    "SHA256": "ce17f2c13a863e4bb3742a0bf2d0e0d5f732cb2c87219aac3f898633127ebb71",
    "Repo": "https://github.com/jqlang/jq"
  },
  {
    "Name": "jwt-cracker.exe",
    "Size": "1.91 MB",
    "ModTime": "2024-05-10T23:36:12.104012100Z",
    "Source": "https://bin.ajam.dev/x64_Windows/jwt-cracker.exe",
    "B3SUM": "cc0661ea5361375fb38927924b32831dde4dc81b1524119a344c1ca9da191c89",
    "SHA256": "272b6b1b1b290d442041b0c538b809abb242c503565df6dbba9b1dffe7bea00c",
    "Repo": "https://github.com/Azathothas/jwt-cracker"
  },
  {
    "Name": "legba.exe",
    "Size": "22.23 MB",
    "ModTime": "2024-05-10T23:36:13.370539400Z",
    "Source": "https://bin.ajam.dev/x64_Windows/legba.exe",
    "B3SUM": "8937c98fb8df6d4c2b9bbb29c483047e933f13deb4f3e03e2567ced624930ced",
    "SHA256": "bbe90def9b54d227d84484bc6ac0a245ba007eefadd34eb24ab13866d643c468",
    "Repo": "https://github.com/evilsocket/legba"
  },
  {
    "Name": "link.exe",
    "Size": "829.95 kB",
    "ModTime": "2024-05-10T23:36:14.088879700Z",
    "Source": "https://bin.ajam.dev/x64_Windows/link.exe",
    "B3SUM": "6340b84c1811d1728ad9d04b4bf37027925cdd2dbfd8c00de7d42c8b06695033",
    "SHA256": "ef19677ac0cb12e73b6e294ac71f3c83da21a944aea92ac4823c1f5965285f8d",
    "Repo": "https://github.com/uutils/coreutils"
  },
  {
    "Name": "ln.exe",
    "Size": "929.79 kB",
    "ModTime": "2024-05-10T23:36:15.089063500Z",
    "Source": "https://bin.ajam.dev/x64_Windows/ln.exe",
    "B3SUM": "a14eed3e48d5f3599be6c6cbc85a03f27646b84f76011ddbc18bca606de39ae7",
    "SHA256": "3b035a7e9a0b3fbbd9e873d4764b953f021eb09ab86e06bf6aafe0d89b7d14fe",
    "Repo": "https://github.com/uutils/coreutils"
  },
  {
    "Name": "localxpose.exe",
    "Size": "23.85 MB",
    "ModTime": "2024-05-10T23:36:16.402219500Z",
    "Source": "https://bin.ajam.dev/x64_Windows/localxpose.exe",
    "B3SUM": null,
    "SHA256": null,
    "Repo": null
  },
  {
    "Name": "loclx.exe",
    "Size": "23.85 MB",
    "ModTime": "2024-05-10T23:36:17.418787600Z",
    "Source": "https://bin.ajam.dev/x64_Windows/loclx.exe",
    "B3SUM": null,
    "SHA256": null,
    "Repo": null
  },
  {
    "Name": "ls.exe",
    "Size": "1.27 MB",
    "ModTime": "2024-05-10T23:36:18.122149000Z",
    "Source": "https://bin.ajam.dev/x64_Windows/ls.exe",
    "B3SUM": "1abfbe1c4078b6581a7c9065f58e0c9f5efd8229a95ddeb43b0e7cae31f94802",
    "SHA256": "42336542be4af2692a4955e2f305c896ee9444ba93069483a561f0b593a13e6b",
    "Repo": "https://github.com/uutils/coreutils"
  },
  {
    "Name": "micro.exe",
    "Size": "11.88 MB",
    "ModTime": "2024-05-10T23:36:19.263036100Z",
    "Source": "https://bin.ajam.dev/x64_Windows/micro.exe",
    "B3SUM": "df07843517b9432e1462cd3ddea36e3391de079ea23fec830b371bc45d32f9ee",
    "SHA256": "ece38dd8e62b628013307e40259e455a788bc2148871edaad24def2dc6e4795b",
    "Repo": "https://github.com/zyedidia/micro"
  },
  {
    "Name": "miniserve.exe",
    "Size": "1.9 MB",
    "ModTime": "2024-03-30T12:20:15.004750200Z",
    "Source": "https://bin.ajam.dev/x64_Windows/miniserve.exe",
    "B3SUM": "cd7cd96ee8095de0a0b6f83fee48c32bf8c2695ad5deb922177a5f1775aab676",
    "SHA256": "060705db94b7ea673486db72ffc54fbd5e3c898758f9a16575d636c78e95dffb",
    "Repo": "https://github.com/svenstaro/miniserve"
  },
  {
    "Name": "mkdir.exe",
    "Size": "839.68 kB",
    "ModTime": "2024-05-10T23:36:21.113629600Z",
    "Source": "https://bin.ajam.dev/x64_Windows/mkdir.exe",
    "B3SUM": "eb99cbcac482a1935523148e5113ba90c9799b754e78f0206601edd911be85f5",
    "SHA256": "039f29c644cdc9423b9602984c18e428203bd7ebaba5f1a987d9c7897cd35797",
    "Repo": "https://github.com/uutils/coreutils"
  },
  {
    "Name": "mktemp.exe",
    "Size": "933.89 kB",
    "ModTime": "2024-05-10T23:36:22.129689800Z",
    "Source": "https://bin.ajam.dev/x64_Windows/mktemp.exe",
    "B3SUM": "55d10d41c565f1173c2848de182e839ab631f7c7a65f37fe9c81f25b1334ab3b",
    "SHA256": "3f6ef9b23bed07c4acd71dba55702c2bd0d55adda6253c33803ade73d686214b",
    "Repo": "https://github.com/uutils/coreutils"
  },
  {
    "Name": "monolith.exe",
    "Size": "5.3 MB",
    "ModTime": "2024-05-10T23:36:23.192453500Z",
    "Source": "https://bin.ajam.dev/x64_Windows/monolith.exe",
    "B3SUM": "8b75531751e10f40269347781ced8ce812305307e358c3aed7232e0a21cd75f4",
    "SHA256": "fed4faa37d7007148c3edc421969a3eff706c661d709af40403f0b3e82391667",
    "Repo": "https://github.com/Y2Z/monolith"
  },
  {
    "Name": "more.exe",
    "Size": "988.16 kB",
    "ModTime": "2024-05-10T23:36:24.130376500Z",
    "Source": "https://bin.ajam.dev/x64_Windows/more.exe",
    "B3SUM": "d5779c94774a4fe92daeacfdec6e43748782d42cde17e3775ebd22c18573b03b",
    "SHA256": "a79a3bdde43cb8a6c9fc8ed5bd7caded3ee4a448a9bc0b0db3df23ebdd6aa7fc",
    "Repo": "https://github.com/uutils/coreutils"
  },
  {
    "Name": "mv.exe",
    "Size": "1.17 MB",
    "ModTime": "2024-05-10T23:36:25.146205800Z",
    "Source": "https://bin.ajam.dev/x64_Windows/mv.exe",
    "B3SUM": "acdea136a2d445786ff92e096981097e3b1aa6b25f2759a262b457b24f00c6ca",
    "SHA256": "cc724659c45f4e8f5ff1e867170f89312164a950ec7f28a9d52fff463bf8d8d8",
    "Repo": "https://github.com/uutils/coreutils"
  },
  {
    "Name": "ngrok.exe",
    "Size": "29.52 MB",
    "ModTime": "2024-05-10T23:36:26.537567000Z",
    "Source": "https://bin.ajam.dev/x64_Windows/ngrok.exe",
    "B3SUM": null,
    "SHA256": null,
    "Repo": null
  },
  {
    "Name": "nl.exe",
    "Size": "2.28 MB",
    "ModTime": "2024-05-10T23:36:27.193804400Z",
    "Source": "https://bin.ajam.dev/x64_Windows/nl.exe",
    "B3SUM": "236f8a501fa089c3e87ed59d089c8fe548bd2394acd6bf2553d613382aa6e071",
    "SHA256": "2eda05728acd793c6c494f458cca57130c8b4ab06ef6ec5c350f263725311f7d",
    "Repo": "https://github.com/uutils/coreutils"
  },
  {
    "Name": "nproc.exe",
    "Size": "828.93 kB",
    "ModTime": "2024-05-10T23:36:28.163399200Z",
    "Source": "https://bin.ajam.dev/x64_Windows/nproc.exe",
    "B3SUM": "61ac30114d86aa66ccf026dfa2326b18807e3fca12ecf6774272fbf0d6e2a2e3",
    "SHA256": "81ecafa1513d1b220f8c8f8a45d04bc3d8c79d1602f0a46cd09bf0ef364f38db",
    "Repo": "https://github.com/uutils/coreutils"
  },
  {
    "Name": "numfmt.exe",
    "Size": "955.9 kB",
    "ModTime": "2024-05-10T23:36:29.163670700Z",
    "Source": "https://bin.ajam.dev/x64_Windows/numfmt.exe",
    "B3SUM": "1ef4c2083ca6847cdb5330bdf4e82434814f0c4dde5116f5967e02a4cc2efe2c",
    "SHA256": "2318634956a110ac85e24974239cc9c4fde662cfbb0c1a807d3702c873db6de3",
    "Repo": "https://github.com/uutils/coreutils"
  },
  {
    "Name": "od.exe",
    "Size": "1 MB",
    "ModTime": "2024-05-10T23:36:30.164257100Z",
    "Source": "https://bin.ajam.dev/x64_Windows/od.exe",
    "B3SUM": "3be019b876be0fcf80f66f83cf794ca34c13e4a1c1ef110f047d4d51eace1456",
    "SHA256": "ddbdeb591bcbb1a56a521daa07bb2014cfe111b6454aba238ddadc8a489d5c1a",
    "Repo": "https://github.com/uutils/coreutils"
  },
  {
    "Name": "openssh.zip",
    "Size": "4.86 MB",
    "ModTime": "2024-04-05T23:44:01.744097900Z",
    "Source": "https://bin.ajam.dev/x64_Windows/openssh.zip",
    "B3SUM": null,
    "SHA256": null,
    "Repo": null
  },
  {
    "Name": "pandoc.exe",
    "Size": "158.98 MB",
    "ModTime": "2024-05-10T23:36:34.718221000Z",
    "Source": "https://bin.ajam.dev/x64_Windows/pandoc.exe",
    "B3SUM": "4a7e048eb50a025ae06e08c199c40c26447795c42da4f80d66a88890b8cece16",
    "SHA256": "5d863d2d8e8d802850f7ef2fe3aba3f01533ce9571ba844b9e1d4b37f9123c1e",
    "Repo": "https://github.com/jgm/pandoc"
  },
  {
    "Name": "paste.exe",
    "Size": "835.07 kB",
    "ModTime": "2024-05-10T23:36:35.171346200Z",
    "Source": "https://bin.ajam.dev/x64_Windows/paste.exe",
    "B3SUM": "34a334c0978818a943bfdd0057161b842b82dfd32bca380e0d0e6ff6b6d2c8be",
    "SHA256": "869db1657f69017ee43f579ca6c184389219dd2d5a5533258a2bdb262a04e487",
    "Repo": "https://github.com/uutils/coreutils"
  },
  {
    "Name": "pdfcpu.exe",
    "Size": "11.55 MB",
    "ModTime": "2024-05-10T23:36:36.318727300Z",
    "Source": "https://bin.ajam.dev/x64_Windows/pdfcpu.exe",
    "B3SUM": "777f85b3988e9dd8b7fcfa0648fd6af2d1016bb78b04dc6809c45aaa00ee7f3b",
    "SHA256": "9f6ae52bd1748ae3df43497ac5eaa7d6a271d717f0eac5b6959a94b731828eac",
    "Repo": "https://github.com/pdfcpu/pdfcpu"
  },
  {
    "Name": "pdfdetach.exe",
    "Size": "1.25 MB",
    "ModTime": "2024-05-10T23:36:37.178158300Z",
    "Source": "https://bin.ajam.dev/x64_Windows/pdfdetach.exe",
    "B3SUM": null,
    "SHA256": null,
    "Repo": null
  },
  {
    "Name": "pdffonts.exe",
    "Size": "1.27 MB",
    "ModTime": "2024-05-10T23:36:38.178809000Z",
    "Source": "https://bin.ajam.dev/x64_Windows/pdffonts.exe",
    "B3SUM": null,
    "SHA256": null,
    "Repo": null
  },
  {
    "Name": "pdfimages.exe",
    "Size": "1.33 MB",
    "ModTime": "2024-05-10T23:36:39.189287400Z",
    "Source": "https://bin.ajam.dev/x64_Windows/pdfimages.exe",
    "B3SUM": null,
    "SHA256": null,
    "Repo": null
  },
  {
    "Name": "pdfinfo.exe",
    "Size": "1.28 MB",
    "ModTime": "2024-05-10T23:36:40.190347200Z",
    "Source": "https://bin.ajam.dev/x64_Windows/pdfinfo.exe",
    "B3SUM": null,
    "SHA256": null,
    "Repo": null
  },
  {
    "Name": "pdftopng.exe",
    "Size": "2.23 MB",
    "ModTime": "2024-05-10T23:36:41.222280100Z",
    "Source": "https://bin.ajam.dev/x64_Windows/pdftopng.exe",
    "B3SUM": null,
    "SHA256": null,
    "Repo": null
  },
  {
    "Name": "pdftoppm.exe",
    "Size": "2.15 MB",
    "ModTime": "2024-05-10T23:36:42.222800100Z",
    "Source": "https://bin.ajam.dev/x64_Windows/pdftoppm.exe",
    "B3SUM": null,
    "SHA256": null,
    "Repo": null
  },
  {
    "Name": "pdftops.exe",
    "Size": "2.34 MB",
    "ModTime": "2024-05-10T23:36:43.223062600Z",
    "Source": "https://bin.ajam.dev/x64_Windows/pdftops.exe",
    "B3SUM": null,
    "SHA256": null,
    "Repo": null
  },
  {
    "Name": "pdftotext.exe",
    "Size": "1.39 MB",
    "ModTime": "2024-05-10T23:36:44.208316200Z",
    "Source": "https://bin.ajam.dev/x64_Windows/pdftotext.exe",
    "B3SUM": null,
    "SHA256": null,
    "Repo": null
  },
  {
    "Name": "pgrok.exe",
    "Size": "10.17 MB",
    "ModTime": "2024-05-10T23:36:45.339115300Z",
    "Source": "https://bin.ajam.dev/x64_Windows/pgrok.exe",
    "B3SUM": "1710201e763880e97a3063fd299fa597c903567d2f37f329c445c2b564efcd5f",
    "SHA256": "d286317ff5b3eda94333b7f1b981454d008e1cbe3eb28325b6063f52ee667803",
    "Repo": "https://github.com/pgrok/pgrok"
  },
  {
    "Name": "pgrokd.exe",
    "Size": "15.67 MB",
    "ModTime": "2024-05-10T23:36:46.417673000Z",
    "Source": "https://bin.ajam.dev/x64_Windows/pgrokd.exe",
    "B3SUM": "74c9ea38fd4834b882b164c108a82062c9778b4e75cf04c7f8014bc23fdc1f24",
    "SHA256": "3f7087be6ae110bfc125e856ce94b8ea94c007fda80dcdc4bc53e99af5e8553d",
    "Repo": "https://github.com/pgrok/pgrok"
  },
  {
    "Name": "pingmole.exe",
    "Size": "3.8 MB",
    "ModTime": "2024-05-10T23:36:47.261663300Z",
    "Source": "https://bin.ajam.dev/x64_Windows/pingmole.exe",
    "B3SUM": "843e927db5486d3397ad527c77689fb92a6831bda6538050f4afb7257742953c",
    "SHA256": "0c5a28582fe1e79bb065655c80e90e3960ef3d558d7c72d9c01888c42f4694ba",
    "Repo": "https://github.com/norskeld/pingmole"
  },
  {
    "Name": "pr.exe",
    "Size": "2.4 MB",
    "ModTime": "2024-05-10T23:36:48.247036600Z",
    "Source": "https://bin.ajam.dev/x64_Windows/pr.exe",
    "B3SUM": "c98be74ac3be190ffded145fd615c3f64ae4f291a91cbd7f5d8fa963cfef28e8",
    "SHA256": "d91abd572b0ebec3c89530108a88cf8fa4d1e5c3ded612d5ecd3c7caaee38aa1",
    "Repo": "https://github.com/uutils/coreutils"
  },
  {
    "Name": "printenv.exe",
    "Size": "803.84 kB",
    "ModTime": "2024-05-10T23:36:49.215917500Z",
    "Source": "https://bin.ajam.dev/x64_Windows/printenv.exe",
    "B3SUM": "e7ea3315fce132dec64352991feeaea5c28607561d3a9ba0e57606a6a916ed14",
    "SHA256": "f809e24ea0d92b9ac26089d95f41f581a88cfc4ba59b0a98df06fb6f35f79b41",
    "Repo": "https://github.com/uutils/coreutils"
  },
  {
    "Name": "printf.exe",
    "Size": "914.94 kB",
    "ModTime": "2024-05-10T23:36:50.218125000Z",
    "Source": "https://bin.ajam.dev/x64_Windows/printf.exe",
    "B3SUM": "a05761438e64cb60dc1d74c984ee84b6a6529dac8fb9d54e94a818bdd6245ae8",
    "SHA256": "2c712191816636233fd2b684448a883174d733c4ef7402f3bb73c4600d1def8c",
    "Repo": "https://github.com/uutils/coreutils"
  },
  {
    "Name": "ptx.exe",
    "Size": "2.37 MB",
    "ModTime": "2024-05-10T23:36:51.249631000Z",
    "Source": "https://bin.ajam.dev/x64_Windows/ptx.exe",
    "B3SUM": "8e7491ba0d7cc7d2d73e24d26e23f505c20513e13daceabce34bdf8de19e0299",
    "SHA256": "1d0c8eca625b368ac6cb306b5c0cc90ce868a6317e0dd9f8ee88ae4d9ed2bb3b",
    "Repo": "https://github.com/uutils/coreutils"
  },
  {
    "Name": "pwd.exe",
    "Size": "820.74 kB",
    "ModTime": "2024-05-10T23:36:52.218737100Z",
    "Source": "https://bin.ajam.dev/x64_Windows/pwd.exe",
    "B3SUM": "e5241dc7ca2b844e0f7c01945d9c4e9a2a3958a45a31a3dad2948467459bfaaf",
    "SHA256": "22116d96a13879ff628b48f9382625014e05ea0b96b21678e05e1a3d6aafdc68",
    "Repo": "https://github.com/uutils/coreutils"
  },
  {
    "Name": "quotes-escaper.exe",
    "Size": "1.56 MB",
    "ModTime": "2024-05-10T23:36:53.219241900Z",
    "Source": "https://bin.ajam.dev/x64_Windows/quotes-escaper.exe",
    "B3SUM": "9a2d1665665e4ea9512878020f68305c100a14d8dc5c631279ab72bba47c2f86",
    "SHA256": "8c510b4cbf39238eebdb3acd237b08ab85cbba5e2d91a03d8d39adad99997bd9",
    "Repo": "hhttps://github.com/Azathothas/Arsenal"
  },
  {
    "Name": "readlink.exe",
    "Size": "880.64 kB",
    "ModTime": "2024-05-10T23:36:54.219591100Z",
    "Source": "https://bin.ajam.dev/x64_Windows/readlink.exe",
    "B3SUM": "95ec6082f7096da33c5f05a5af3b3ff180719f6fd78a177c330e453d8eea7f50",
    "SHA256": "06c95b116c93a29ffa45bc37d57c935a89284046cde727dbd99454db5d433c03",
    "Repo": "https://github.com/uutils/coreutils"
  },
  {
    "Name": "realpath.exe",
    "Size": "884.22 kB",
    "ModTime": "2024-05-10T23:36:55.219755700Z",
    "Source": "https://bin.ajam.dev/x64_Windows/realpath.exe",
    "B3SUM": "0a8a489a14c52a208c0d8f719fbea5dca05f218284a634f3f88afd226cd2e594",
    "SHA256": "b9f67af7a763148e01f8ca3f6002592302ce5baac58ecbc73eeb02bee0b9bbc6",
    "Repo": "https://github.com/uutils/coreutils"
  },
  {
    "Name": "rg.exe",
    "Size": "5.33 MB",
    "ModTime": "2024-05-10T23:36:56.282575200Z",
    "Source": "https://bin.ajam.dev/x64_Windows/rg.exe",
    "B3SUM": "94680a51b9e8419d4971ec4a0ab010ee5142ec65a4881e5f9349c4d5be4e21c4",
    "SHA256": "391cd26ec341ad072cf8b76aa08857372acf859904a92d762b34665aa49a2fac",
    "Repo": "https://github.com/BurntSushi/ripgrep"
  },
  {
    "Name": "rm.exe",
    "Size": "909.82 kB",
    "ModTime": "2024-05-10T23:36:57.220605600Z",
    "Source": "https://bin.ajam.dev/x64_Windows/rm.exe",
    "B3SUM": "1d37aeed0530cc259087b32da5b7166c93e8b2075504ef73d23c0b21b9811508",
    "SHA256": "ac01a3cbb017086f0d424f870a9b2a682c0ba4580ea81bb71d48482349a73663",
    "Repo": "https://github.com/uutils/coreutils"
  },
  {
    "Name": "rmdir.exe",
    "Size": "835.07 kB",
    "ModTime": "2024-05-10T23:36:58.221140300Z",
    "Source": "https://bin.ajam.dev/x64_Windows/rmdir.exe",
    "B3SUM": "cd22d70f276d50e31ef35c9c1b394d62f91de20978a8e238610f54283e232398",
    "SHA256": "e91b148ff9d32ab95b9123ba371b62426e39b6045118138a1ed425dfbd71b143",
    "Repo": "https://github.com/uutils/coreutils"
  },
  {
    "Name": "scp.exe",
    "Size": "456.7 kB",
    "ModTime": "2024-05-10T23:36:59.205696900Z",
    "Source": "https://bin.ajam.dev/x64_Windows/scp.exe",
    "B3SUM": null,
    "SHA256": null,
    "Repo": null
  },
  {
    "Name": "seq.exe",
    "Size": "1.04 MB",
    "ModTime": "2024-05-10T23:37:00.221840600Z",
    "Source": "https://bin.ajam.dev/x64_Windows/seq.exe",
    "B3SUM": "cf56d92d71fa7c2cc061b2d44aed14887df61060903aab45daa714b353e2287d",
    "SHA256": "c7aae32871d4d25ee228e2fbb3d2bad18afc08b0e81a4bd47da33da9e19aee8c",
    "Repo": "https://github.com/uutils/coreutils"
  },
  {
    "Name": "sftp-server.exe",
    "Size": "374.27 kB",
    "ModTime": "2024-05-10T23:37:01.206530000Z",
    "Source": "https://bin.ajam.dev/x64_Windows/sftp-server.exe",
    "B3SUM": null,
    "SHA256": null,
    "Repo": null
  },
  {
    "Name": "shred.exe",
    "Size": "897.54 kB",
    "ModTime": "2024-05-10T23:37:02.222382700Z",
    "Source": "https://bin.ajam.dev/x64_Windows/shred.exe",
    "B3SUM": "03028364bc7a0235380c0bbf219d40e63ef5ba758c36ffe3eacbf878f1b9d54d",
    "SHA256": "0dc101eb14c913b5561a80e89b01d72ccb50dd70d42461381c9e57d21883a40c",
    "Repo": "https://github.com/uutils/coreutils"
  },
  {
    "Name": "shuf.exe",
    "Size": "911.87 kB",
    "ModTime": "2024-05-10T23:37:03.222579600Z",
    "Source": "https://bin.ajam.dev/x64_Windows/shuf.exe",
    "B3SUM": "8c22177ea03c45c258c6521e2d83ef74d410a9b762b0ea4b49d7f71a796a3ff0",
    "SHA256": "7789d938d449c041e604cd6f2cbfd7307f8a789890fe498234aa0f97349fe9e7",
    "Repo": "https://github.com/uutils/coreutils"
  },
  {
    "Name": "sing-box.exe",
    "Size": "30.45 MB",
    "ModTime": "2024-05-10T23:37:04.620676500Z",
    "Source": "https://bin.ajam.dev/x64_Windows/sing-box.exe",
    "B3SUM": "7d013b5c499675a0f4c49ffeaa3624adcfaa1b9b1c77ccea4093681ea8664cfe",
    "SHA256": "e8e7c6ce30942eba0e3458feccd9debac059645b45a42f310ad225467f2cca56",
    "Repo": "https://github.com/SagerNet/sing-box"
  },
  {
    "Name": "sish.exe",
    "Size": "20.42 MB",
    "ModTime": "2024-05-10T23:37:05.496219000Z",
    "Source": "https://bin.ajam.dev/x64_Windows/sish.exe",
    "B3SUM": "100ea58d26d63c3f898c120d8d7f71a7b042d24c4dfced7c2a4952d1bd7a8b26",
    "SHA256": "62b8373255468c24cd6e0cc019e5d59db6e957abfaa3c5758754d3064ff5bdcd",
    "Repo": "https://github.com/antoniomika/sish"
  },
  {
    "Name": "sleep.exe",
    "Size": "839.17 kB",
    "ModTime": "2024-05-10T23:37:06.230761800Z",
    "Source": "https://bin.ajam.dev/x64_Windows/sleep.exe",
    "B3SUM": "ee914e236f27c8fc7dd3796ca04039aec05b2fada82c915110b5a92234f88482",
    "SHA256": "a807f52c3d3f51b0f527906cf869b2993169e66529d153c99182f4f761ee3cda",
    "Repo": "https://github.com/uutils/coreutils"
  },
  {
    "Name": "smartdns.exe",
    "Size": "9.36 MB",
    "ModTime": "2024-05-11T18:00:17.222845600Z",
    "Source": "https://bin.ajam.dev/x64_Windows/smartdns.exe",
    "B3SUM": null,
    "SHA256": null,
    "Repo": null
  },
  {
    "Name": "sort.exe",
    "Size": "1.67 MB",
    "ModTime": "2024-05-10T23:37:07.246719800Z",
    "Source": "https://bin.ajam.dev/x64_Windows/sort.exe",
    "B3SUM": "1c23f191cfbf18a12e6647b61c17154d80634f9e40d4e76177abad8041c98a43",
    "SHA256": "d4fc5bf9d741b0f30ddb42667083e763fc1f15c04ffba51504f1987a881b24d1",
    "Repo": "https://github.com/uutils/coreutils"
  },
  {
    "Name": "split.exe",
    "Size": "966.14 kB",
    "ModTime": "2024-05-10T23:37:08.240348500Z",
    "Source": "https://bin.ajam.dev/x64_Windows/split.exe",
    "B3SUM": "ae1815319ff8e1a5b88763679a06364b48e9cf32451f8e0be5797702489d00bb",
    "SHA256": "8ac6fb6243e116dad579b62666b565911e28b5b7474d724a64700f9ee1fbbd08",
    "Repo": "https://github.com/uutils/coreutils"
  },
  {
    "Name": "ssh-add.exe",
    "Size": "604.67 kB",
    "ModTime": "2024-05-10T23:37:09.240604800Z",
    "Source": "https://bin.ajam.dev/x64_Windows/ssh-add.exe",
    "B3SUM": null,
    "SHA256": null,
    "Repo": null
  },
  {
    "Name": "ssh-agent.exe",
    "Size": "556.03 kB",
    "ModTime": "2024-05-10T23:37:10.241313200Z",
    "Source": "https://bin.ajam.dev/x64_Windows/ssh-agent.exe",
    "B3SUM": null,
    "SHA256": null,
    "Repo": null
  },
  {
    "Name": "ssh-keygen.exe",
    "Size": "854.53 kB",
    "ModTime": "2024-05-10T23:37:11.241774900Z",
    "Source": "https://bin.ajam.dev/x64_Windows/ssh-keygen.exe",
    "B3SUM": null,
    "SHA256": null,
    "Repo": null
  },
  {
    "Name": "ssh-keyscan.exe",
    "Size": "665.09 kB",
    "ModTime": "2024-05-10T23:37:12.249497800Z",
    "Source": "https://bin.ajam.dev/x64_Windows/ssh-keyscan.exe",
    "B3SUM": null,
    "SHA256": null,
    "Repo": null
  },
  {
    "Name": "ssh-pkcs11-helper.exe",
    "Size": "519.68 kB",
    "ModTime": "2024-05-10T23:37:13.250633700Z",
    "Source": "https://bin.ajam.dev/x64_Windows/ssh-pkcs11-helper.exe",
    "B3SUM": null,
    "SHA256": null,
    "Repo": null
  },
  {
    "Name": "ssh-shellhost.exe",
    "Size": "179.2 kB",
    "ModTime": "2024-05-10T23:37:14.257561900Z",
    "Source": "https://bin.ajam.dev/x64_Windows/ssh-shellhost.exe",
    "B3SUM": null,
    "SHA256": null,
    "Repo": null
  },
  {
    "Name": "ssh-sk-helper.exe",
    "Size": "659.46 kB",
    "ModTime": "2024-05-10T23:37:15.273333500Z",
    "Source": "https://bin.ajam.dev/x64_Windows/ssh-sk-helper.exe",
    "B3SUM": null,
    "SHA256": null,
    "Repo": null
  },
  {
    "Name": "ssh.exe",
    "Size": "1.24 MB",
    "ModTime": "2024-05-10T23:37:16.278262300Z",
    "Source": "https://bin.ajam.dev/x64_Windows/ssh.exe",
    "B3SUM": null,
    "SHA256": null,
    "Repo": null
  },
  {
    "Name": "sshd.exe",
    "Size": "1.33 MB",
    "ModTime": "2024-05-10T23:37:17.278871100Z",
    "Source": "https://bin.ajam.dev/x64_Windows/sshd.exe",
    "B3SUM": null,
    "SHA256": null,
    "Repo": null
  },
  {
    "Name": "stP1kAlM",
    "Size": "0 B",
    "ModTime": "2024-03-30T12:20:45.532136400Z",
    "Source": "https://bin.ajam.dev/x64_Windows/stP1kAlM",
    "B3SUM": null,
    "SHA256": null,
    "Repo": null
  },
  {
    "Name": "step.exe",
    "Size": "37.12 MB",
    "ModTime": "2024-05-10T23:37:18.764670800Z",
    "Source": "https://bin.ajam.dev/x64_Windows/step.exe",
    "B3SUM": "4213bca583076b38952d931f92bdf0141e4bf6a01fe32ef6d0d96919343aae0a",
    "SHA256": "9d2033ea7a1f7b20d531abfdda96ffc41498b259987c678d86cf99430c0e7286",
    "Repo": "https://github.com/smallstep/cli"
  },
  {
    "Name": "stiG2Kb7",
    "Size": "0 B",
    "ModTime": "2024-03-30T12:20:46.532861400Z",
    "Source": "https://bin.ajam.dev/x64_Windows/stiG2Kb7",
    "B3SUM": null,
    "SHA256": null,
    "Repo": null
  },
  {
    "Name": "sum.exe",
    "Size": "849.41 kB",
    "ModTime": "2024-05-10T23:37:19.280303100Z",
    "Source": "https://bin.ajam.dev/x64_Windows/sum.exe",
    "B3SUM": "717e57d7f1bbb533f67b9f8a91922fd3cb9d566fb3310ca981d8aed35e7d79f0",
    "SHA256": "a36ea0001671dadfd6cc58ff20a56c32641791033b7b0bc10d998c21225922a5",
    "Repo": "https://github.com/uutils/coreutils"
  },
  {
    "Name": "sync.exe",
    "Size": "835.58 kB",
    "ModTime": "2024-05-10T23:37:20.281044900Z",
    "Source": "https://bin.ajam.dev/x64_Windows/sync.exe",
    "B3SUM": "c006b6e5c60362ead69de0e7e4ed2082d77246e94c1bbe4755b37b2a6c95d65c",
    "SHA256": "d21dbc5bb99841e322e22d54958fb70cd9c258590635064bc21be1d811ab095d",
    "Repo": "https://github.com/uutils/coreutils"
  },
  {
    "Name": "tac.exe",
    "Size": "2.25 MB",
    "ModTime": "2024-05-10T23:37:21.296837800Z",
    "Source": "https://bin.ajam.dev/x64_Windows/tac.exe",
    "B3SUM": "b661ad6e84135bf2930e693fcbe8f04b696a38b3d6cfa2cb6eb5fd9d41e5bbaa",
    "SHA256": "e121e31d081ed69a29b510da49d5954e450188726908062759ed4466e3ca20d8",
    "Repo": "https://github.com/uutils/coreutils"
  },
  {
    "Name": "tail.exe",
    "Size": "1.33 MB",
    "ModTime": "2024-05-10T23:37:22.288087300Z",
    "Source": "https://bin.ajam.dev/x64_Windows/tail.exe",
    "B3SUM": "b0d836531934ce7baa4fa9ebc3cc90de86df01d943c4fcd8918a8329b10542e0",
    "SHA256": "ea5b32e08824cc24698a8f23b4dc27fd861b5235829fee97d5323c366f340dcf",
    "Repo": "https://github.com/uutils/coreutils"
  },
  {
    "Name": "tee.exe",
    "Size": "874.5 kB",
    "ModTime": "2024-05-10T23:37:23.288582300Z",
    "Source": "https://bin.ajam.dev/x64_Windows/tee.exe",
    "B3SUM": "03a5ceff934efdf7ea7b51e1ba7340c6e9379abea62755a38d1b0ff0a1e8563f",
    "SHA256": "a55971d73010b179ebba3c47d7a0dc37d13a82553261f1586723bd7b9552c4e5",
    "Repo": "https://github.com/uutils/coreutils"
  },
  {
    "Name": "test.exe",
    "Size": "846.34 kB",
    "ModTime": "2024-05-10T23:37:24.289107500Z",
    "Source": "https://bin.ajam.dev/x64_Windows/test.exe",
    "B3SUM": "c7307e9bc19bb0494f3bd9de343da77c3a0f595b027a50d58ab60d4f6fa2b6a1",
    "SHA256": "93daf79c138a1c56403a7c081959255270a598c37b09fd499da79104f04e8516",
    "Repo": "https://github.com/uutils/coreutils"
  },
  {
    "Name": "touch.exe",
    "Size": "2.36 MB",
    "ModTime": "2024-05-10T23:37:25.320541700Z",
    "Source": "https://bin.ajam.dev/x64_Windows/touch.exe",
    "B3SUM": "24581a6bcb0d8254e6b1e4f7ed268004f8aaf9066545fa8610ac805b03dfac50",
    "SHA256": "c93f950ca88293e583721b448132eda57dd3e03a3b415716f2cac60627906c99",
    "Repo": "https://github.com/uutils/coreutils"
  },
  {
    "Name": "tr.exe",
    "Size": "902.14 kB",
    "ModTime": "2024-05-10T23:37:26.298756700Z",
    "Source": "https://bin.ajam.dev/x64_Windows/tr.exe",
    "B3SUM": "0a49bcae658d0496da1a051688905d83e3e9dfeea685d1632bba77e4f3da1101",
    "SHA256": "a27d31457e727399e9cf9bc116334138dc729124dca88f03df5dcfdce6a5b180",
    "Repo": "https://github.com/uutils/coreutils"
  },
  {
    "Name": "true.exe",
    "Size": "758.78 kB",
    "ModTime": "2024-05-10T23:37:27.301885100Z",
    "Source": "https://bin.ajam.dev/x64_Windows/true.exe",
    "B3SUM": "68dace15c3338b8cdb6a74eabbb553814a3b0d8690701d6217da28587b62c631",
    "SHA256": "018b2f911fd43fa60781f008faa305574d61d7cb571d0eb423853bab3d5b5f03",
    "Repo": "https://github.com/uutils/coreutils"
  },
  {
    "Name": "truncate.exe",
    "Size": "844.29 kB",
    "ModTime": "2024-05-10T23:37:28.302270200Z",
    "Source": "https://bin.ajam.dev/x64_Windows/truncate.exe",
    "B3SUM": "3ce917e967987a554a595f1cdaca2959db91b239c61fb1df64bd1e20f23d391d",
    "SHA256": "90e297a61134a2824083ae3e5d3bd0815fda8e04d0e328f2946328246975422f",
    "Repo": "https://github.com/uutils/coreutils"
  },
  {
    "Name": "trurl.exe",
    "Size": "7.04 MB",
    "ModTime": "2024-05-10T23:37:29.380539400Z",
    "Source": "https://bin.ajam.dev/x64_Windows/trurl.exe",
    "B3SUM": "2ad8dddfab873fcc5cce568f6c9bc146ad3c2236b785ee3eecced2ea34faf342",
    "SHA256": "17cdbcfc078bc1f71eae3b9feb4592119692b2ae33cc0e64f10eb372d7b24ed0",
    "Repo": "https://github.com/stunnel/static-curl"
  },
  {
    "Name": "tsort.exe",
    "Size": "879.1 kB",
    "ModTime": "2024-05-10T23:37:30.303021800Z",
    "Source": "https://bin.ajam.dev/x64_Windows/tsort.exe",
    "B3SUM": "b2ea9526d332dd4769c7dd01e796b35f7d610c797ca1a9a7c5657868606255cb",
    "SHA256": "aebfb93e3c2ecdbeaf76304784af5b4e8ce87c856c89200e281eb2e0731fcbc5",
    "Repo": "https://github.com/uutils/coreutils"
  },
  {
    "Name": "tssh.exe",
    "Size": "10.84 MB",
    "ModTime": "2024-05-10T23:37:31.428194400Z",
    "Source": "https://bin.ajam.dev/x64_Windows/tssh.exe",
    "B3SUM": "f0caf57a09c4b88cdbeec63f2b04c8481aa3b7cfb0f22cb938b4b050cf7fd54a",
    "SHA256": "379c781ac9972b43d6d38f299ab0b5c6de1902da7fb9ee7377f89a5c8bde4811",
    "Repo": "https://github.com/trzsz/trzsz-ssh"
  },
  {
    "Name": "uname.exe",
    "Size": "847.36 kB",
    "ModTime": "2024-05-10T23:37:32.303949800Z",
    "Source": "https://bin.ajam.dev/x64_Windows/uname.exe",
    "B3SUM": "e7b15c793ea93be7d022854fc804f39c3fd638491b0704458dece8485006ff6d",
    "SHA256": "f3ab31df3bc00a9befc014ea01248b732f819db7cea67db6a7d6fc8028a2b904",
    "Repo": "https://github.com/uutils/coreutils"
  },
  {
    "Name": "unexpand.exe",
    "Size": "870.91 kB",
    "ModTime": "2024-05-10T23:37:33.304428900Z",
    "Source": "https://bin.ajam.dev/x64_Windows/unexpand.exe",
    "B3SUM": "7f053ec91ca111bdfd4ca7be6da4ed235c24fcd1b58c335e17759807b35276f3",
    "SHA256": "834db3089c31d595f18f114ef70670a4f4db5384634ade8ce8735a56a8bfff1d",
    "Repo": "https://github.com/uutils/coreutils"
  },
  {
    "Name": "uniq.exe",
    "Size": "906.75 kB",
    "ModTime": "2024-05-10T23:37:34.306229400Z",
    "Source": "https://bin.ajam.dev/x64_Windows/uniq.exe",
    "B3SUM": "2b02cc22c97e7717711fc4e5dd6e8969072ac55e4e489b39c7d6bbee55ca2b0b",
    "SHA256": "5fc42cf1821158571e24326f6e41c4ef988c5ca32ce6d3253defc5882e3efc8b",
    "Repo": "https://github.com/uutils/coreutils"
  },
  {
    "Name": "unlink.exe",
    "Size": "828.42 kB",
    "ModTime": "2024-05-10T23:37:35.306362500Z",
    "Source": "https://bin.ajam.dev/x64_Windows/unlink.exe",
    "B3SUM": "a66f5abeea36c47d0b41ba3d8e3521e870e1e51422818e51ddfd3f54cc2a6168",
    "SHA256": "d8bc39b8d657088e9222e0118e4fb06d2950f0aab6deaf2bd0a70ca7ce99114a",
    "Repo": "https://github.com/uutils/coreutils"
  },
  {
    "Name": "upx.exe",
    "Size": "564.22 kB",
    "ModTime": "2024-03-29T11:24:05.355607900Z",
    "Source": "https://bin.ajam.dev/x64_Windows/upx.exe",
    "B3SUM": null,
    "SHA256": null,
    "Repo": null
  },
  {
    "Name": "vdir.exe",
    "Size": "1.25 MB",
    "ModTime": "2024-05-10T23:37:36.312716700Z",
    "Source": "https://bin.ajam.dev/x64_Windows/vdir.exe",
    "B3SUM": "550cd8b6b8fab13728ab16ff73fd5df1da3adb40b25f771abc9108fc24e16218",
    "SHA256": "c478d80a4f238f7b5df254137b2cbe7857cb64380c440345299428ac8db12e24",
    "Repo": "https://github.com/uutils/coreutils"
  },
  {
    "Name": "wc.exe",
    "Size": "922.62 kB",
    "ModTime": "2024-05-10T23:37:37.312916200Z",
    "Source": "https://bin.ajam.dev/x64_Windows/wc.exe",
    "B3SUM": "f53ceaf24fb65cc839076fde79c8ad0b286db54ffb2df8cf63d6d12557b35465",
    "SHA256": "edb16865e89d277bf39c12ea6ab7e514aef0cd0b49daef4f101cb1f5c3305780",
    "Repo": "https://github.com/uutils/coreutils"
  },
  {
    "Name": "wget2.exe",
    "Size": "4.61 MB",
    "ModTime": "2024-05-10T23:37:38.360474700Z",
    "Source": "https://bin.ajam.dev/x64_Windows/wget2.exe",
    "B3SUM": "55c55d7ce68dd2676e5ddd8a653ddb0078b8e25b632c5cc21b7b1535e2362f5a",
    "SHA256": "4dfd3b67b37ffb641b480eb248992a311a12bd1dd6e6a0fd4abba8ac336fd570",
    "Repo": "https://github.com/rockdaboot/wget2"
  },
  {
    "Name": "whoami.exe",
    "Size": "810.5 kB",
    "ModTime": "2024-05-10T23:37:39.313735800Z",
    "Source": "https://bin.ajam.dev/x64_Windows/whoami.exe",
    "B3SUM": "b37620e0faee989bd48b6b1b6e7e78158a598d370943f2acdf3e06592e28a37d",
    "SHA256": "357803acd841a6a04780ad576da5fe7c44bd1e9e5da5851e204aaee31a6718aa",
    "Repo": "https://github.com/uutils/coreutils"
  },
  {
    "Name": "wldd.exe",
    "Size": "1.24 MB",
    "ModTime": "2024-05-10T23:37:40.314685100Z",
    "Source": "https://bin.ajam.dev/x64_Windows/wldd.exe",
    "B3SUM": "3a7d2e202a09989323d660a36214ad68650a4e9ef20f357b37f3ec65aeb370df",
    "SHA256": "f48bbacac424f6c757697489500466da9ad5d064afb40c371d65661540159ff4",
    "Repo": "https://github.com/marcoesposito1988/dependency_runner"
  },
  {
    "Name": "xargs-rs.exe",
    "Size": "884.22 kB",
    "ModTime": "2024-05-10T23:37:41.315590400Z",
    "Source": "https://bin.ajam.dev/x64_Windows/xargs-rs.exe",
    "B3SUM": "be8f9d2d64dd70f3c0f9d998183d0aac6753e166ffc5c592914ca9a9dad39dd0",
    "SHA256": "15b54f0b154703df1368df2801d313216d5ed169dd593fbed75121fb4e165466",
    "Repo": "https://github.com/uutils/findutils"
  },
  {
    "Name": "xargs.exe",
    "Size": "884.22 kB",
    "ModTime": "2024-05-10T23:37:42.316032700Z",
    "Source": "https://bin.ajam.dev/x64_Windows/xargs.exe",
    "B3SUM": "ccbcdc793cc5daaff13fb3d415946ad8115760ef5e9bbc85af3d46cece4c9d51",
    "SHA256": "69af987ab5f1dc87cb21784c115ff1f2c49fced3a72785038234e700e962d445",
    "Repo": "https://github.com/uutils/findutils"
  },
  {
    "Name": "yes.exe",
    "Size": "807.42 kB",
    "ModTime": "2024-05-10T23:37:43.316299200Z",
    "Source": "https://bin.ajam.dev/x64_Windows/yes.exe",
    "B3SUM": "30a31c3d96f6a8b15ea8f074e0c38b67364e220b8bb6ad54acee7973b3ab4045",
    "SHA256": "3aa37aff4e22e20b368a27dcc6168dc5bd7414469e8c0c387ad352e643ae7c84",
    "Repo": "https://github.com/uutils/coreutils"
  },
  {
    "Name": "yq.exe",
    "Size": "10.35 MB",
    "ModTime": "2024-03-29T11:24:05.312053200Z",
    "Source": "https://bin.ajam.dev/x64_Windows/yq.exe",
    "B3SUM": null,
    "SHA256": null,
    "Repo": null
  },
  {
    "Name": "yt-dlp.exe",
    "Size": "173.06 kB",
    "ModTime": "2024-05-10T23:37:44.301019500Z",
    "Source": "https://bin.ajam.dev/x64_Windows/yt-dlp.exe",
    "B3SUM": "00171e51ed8e7cc9141e23a6e65affc6a48e4143beaca1b68522f1f030d06d7b",
    "SHA256": "8cacf558c024ef1011e4f2bf16ffed226bac3c88fa39dce309882fafe472f5ac",
    "Repo": "https://github.com/yt-dlp/yt-dlp"
  }
]
