[
  {
    "Name": "7z.exe",
    "Size": "1.32 MB",
    "ModTime": "2024-05-17T23:41:50.032222800Z",
    "Source": "https://bin.ajam.dev/x64_Windows/7z.exe",
    "B3SUM": null,
    "SHA256": null,
    "Repo": null
  },
  {
    "Name": "BLAKE3SUM.txt",
    "Size": "13.86 kB",
    "ModTime": "2024-05-17T23:45:20.096459900Z",
    "Source": "https://bin.ajam.dev/x64_Windows/BLAKE3SUM.txt",
    "B3SUM": null,
    "SHA256": null,
    "Repo": null
  },
  {
    "Name": "BUILD.log.txt",
    "Size": "836.09 kB",
    "ModTime": "2024-05-17T23:48:15.014043200Z",
    "Source": "https://bin.ajam.dev/x64_Windows/BUILD.log.txt",
    "B3SUM": null,
    "SHA256": null,
    "Repo": null
  },
  {
    "Name": "FILE.txt",
    "Size": "20.16 kB",
    "ModTime": "2024-05-12T23:38:29.099319700Z",
    "Source": "https://bin.ajam.dev/x64_Windows/FILE.txt",
    "B3SUM": null,
    "SHA256": null,
    "Repo": null
  },
  {
    "Name": "METADATA.json",
    "Size": "64.48 kB",
    "ModTime": "2024-05-19T00:20:43.944963900Z",
    "Source": "https://bin.ajam.dev/x64_Windows/METADATA.json",
    "B3SUM": null,
    "SHA256": null,
    "Repo": null
  },
  {
    "Name": "SHA256SUM.txt",
    "Size": "13.86 kB",
    "ModTime": "2024-05-17T23:45:27.177989500Z",
    "Source": "https://bin.ajam.dev/x64_Windows/SHA256SUM.txt",
    "B3SUM": null,
    "SHA256": null,
    "Repo": null
  },
  {
    "Name": "SIZE.txt",
    "Size": "5152 B",
    "ModTime": "2024-05-17T23:45:16.949967100Z",
    "Source": "https://bin.ajam.dev/x64_Windows/SIZE.txt",
    "B3SUM": null,
    "SHA256": null,
    "Repo": null
  },
  {
    "Name": "_toolpack_x64_Windows.7z",
    "Size": "300.66 MB",
    "ModTime": "2024-05-17T23:47:58.319449500Z",
    "Source": "https://bin.ajam.dev/x64_Windows/_toolpack_x64_Windows.7z",
    "B3SUM": null,
    "SHA256": null,
    "Repo": null
  },
  {
    "Name": "_toolpack_x64_Windows_BLAKE3SUM.txt",
    "Size": "93 B",
    "ModTime": "2024-05-17T23:48:10.334514600Z",
    "Source": "https://bin.ajam.dev/x64_Windows/_toolpack_x64_Windows_BLAKE3SUM.txt",
    "B3SUM": null,
    "SHA256": null,
    "Repo": null
  },
  {
    "Name": "_toolpack_x64_Windows_SHA256SUM.txt",
    "Size": "95 B",
    "ModTime": "2024-05-17T23:48:13.291945600Z",
    "Source": "https://bin.ajam.dev/x64_Windows/_toolpack_x64_Windows_SHA256SUM.txt",
    "B3SUM": null,
    "SHA256": null,
    "Repo": null
  },
  {
    "Name": "actionlint.exe",
    "Size": "5.41 MB",
    "ModTime": "2024-05-17T23:41:50.330122200Z",
    "Source": "https://bin.ajam.dev/x64_Windows/actionlint.exe",
    "B3SUM": "1852116ea9b90c0bb4b3e6f84d7d25a6006b17dd67259f30842d6dad93b7cae7",
    "SHA256": "ac1ec71870af5dee3ab67fc5a9b4d810e6c59726967cc4823c872bfab96e0faf",
    "Repo": "https://github.com/rhysd/actionlint"
  },
  {
    "Name": "age.exe",
    "Size": "3.88 MB",
    "ModTime": "2024-05-17T23:41:51.314743200Z",
    "Source": "https://bin.ajam.dev/x64_Windows/age.exe",
    "B3SUM": "3fdf7f55ce5df9aa9b9fed8f4e4bbadfc946d049b5208b667f07a469015092cb",
    "SHA256": "27ecf8aef045a20553e6e61bb75adb080e4926e58f3da0b295597496851f644f",
    "Repo": "https://github.com/FiloSottile/age"
  },
  {
    "Name": "algernon.exe",
    "Size": "26.77 MB",
    "ModTime": "2024-05-17T23:41:52.612359700Z",
    "Source": "https://bin.ajam.dev/x64_Windows/algernon.exe",
    "B3SUM": "c3d9c76ad999cadcfce89cfb5cc264f395f331523ccc22ee4089b6cd8df329e0",
    "SHA256": "87e683d10d1214b07b71c85e558027ca00baa577807f9ca9ab6db86660e29975",
    "Repo": "https://github.com/xyproto/algernon"
  },
  {
    "Name": "alist.exe",
    "Size": "66.83 MB",
    "ModTime": "2024-05-17T23:41:54.159761700Z",
    "Source": "https://bin.ajam.dev/x64_Windows/alist.exe",
    "B3SUM": "ea62fcf800b87116969b9b270b587d52fc2178ae5dd5cd545491bf6598c43453",
    "SHA256": "e7d1b34f41b264632c56a9eff8c0322787b7a625cb9ecfa7d8bcdeaa2ccb81f9",
    "Repo": "https://github.com/alist-org/alist"
  },
  {
    "Name": "anew-rs.exe",
    "Size": "787.46 kB",
    "ModTime": "2024-05-17T23:41:54.269141000Z",
    "Source": "https://bin.ajam.dev/x64_Windows/anew-rs.exe",
    "B3SUM": "0d05f0c4c4864e3c2bf10f5532228f0ec2b8f0319d576600f883897715707d28",
    "SHA256": "175717a6eb8f80abf58ee404defbf024dd288cf162433adc8dd167d12baea385",
    "Repo": "https://github.com/zer0yu/anew"
  },
  {
    "Name": "anew.exe",
    "Size": "787.46 kB",
    "ModTime": "2024-05-17T23:41:55.270608700Z",
    "Source": "https://bin.ajam.dev/x64_Windows/anew.exe",
    "B3SUM": "eb298dbbcc5cce30e589a84c2b93d38c99f41967922da1745cf956c785c5478d",
    "SHA256": "111fe61660d060080597f51d4b5ca370bf17a8a10c8ed719b5a4be179eae74d8",
    "Repo": "https://github.com/zer0yu/anew"
  },
  {
    "Name": "arch.exe",
    "Size": "826.37 kB",
    "ModTime": "2024-05-17T23:41:56.271150900Z",
    "Source": "https://bin.ajam.dev/x64_Windows/arch.exe",
    "B3SUM": "5d5e4cbcd20c9ce0c5ce9997a0f9c1bb1582bcba547e347f205885fc915ec11a",
    "SHA256": "801d5f782570116f6b52ec45e2df092081b821ff27d32e09f31861cba476a400",
    "Repo": "https://github.com/uutils/coreutils"
  },
  {
    "Name": "b3sum.exe",
    "Size": "1.06 MB",
    "ModTime": "2024-05-17T23:41:57.271429000Z",
    "Source": "https://bin.ajam.dev/x64_Windows/b3sum.exe",
    "B3SUM": "cba1d061218f74ac88fae7794defed0d6592ccdf09304b72af0cb1280ef51a58",
    "SHA256": "08fb019997b9b9db5a0c71361243f647d6a99e56994cb86da645c597f514cce9",
    "Repo": "https://github.com/BLAKE3-team/BLAKE3"
  },
  {
    "Name": "base32.exe",
    "Size": "944.13 kB",
    "ModTime": "2024-05-17T23:41:58.271968200Z",
    "Source": "https://bin.ajam.dev/x64_Windows/base32.exe",
    "B3SUM": "5b6a5ea7335a239fe8a1dcdb695d7fca5341c039aed28f658d0fc036d119c123",
    "SHA256": "b9379204015e4f6d6fb2e77208719608c175d5a3027d2004d31ea0d4d308f78d",
    "Repo": "https://github.com/uutils/coreutils"
  },
  {
    "Name": "base64.exe",
    "Size": "944.64 kB",
    "ModTime": "2024-05-17T23:41:59.272184700Z",
    "Source": "https://bin.ajam.dev/x64_Windows/base64.exe",
    "B3SUM": "c61aad16410871372155e91814214daf9bfb209b31d0ae16fe7c5e7ceaca4843",
    "SHA256": "048b168a4f165b1ac534472a99a76c868295cfe4e5f3d56734a3a72c9e50fb6b",
    "Repo": "https://github.com/uutils/coreutils"
  },
  {
    "Name": "basename.exe",
    "Size": "840.19 kB",
    "ModTime": "2024-05-17T23:42:00.272718400Z",
    "Source": "https://bin.ajam.dev/x64_Windows/basename.exe",
    "B3SUM": "97aa47f9491b433657c1b0512c4f54a4b0407affec4f7b99d28b6b3d82ef57e5",
    "SHA256": "2615ac16505501f74921c3bb38eb025f2a735c69720aea909f34610bb20692fb",
    "Repo": "https://github.com/uutils/coreutils"
  },
  {
    "Name": "basenc.exe",
    "Size": "968.7 kB",
    "ModTime": "2024-05-17T23:42:01.273593800Z",
    "Source": "https://bin.ajam.dev/x64_Windows/basenc.exe",
    "B3SUM": "bd215ccb6c3ce81d5d716b19e27226549a89f26af575acd739502185803e9172",
    "SHA256": "754f43f5738855b38516cb88bd0b311bc631c4021348356ae3d4f31c2fc5be26",
    "Repo": "https://github.com/uutils/coreutils"
  },
  {
    "Name": "bat.exe",
    "Size": "6.32 MB",
    "ModTime": "2024-05-17T23:42:02.352458200Z",
    "Source": "https://bin.ajam.dev/x64_Windows/bat.exe",
    "B3SUM": "7de5a4fec58987dcebbfff873590e93970f394b546e8afcf193a7828a652976c",
    "SHA256": "5a4130f0c09a8b96dc6c64e9643cbff6779abae9d9b93e557aef6bc517bdc589",
    "Repo": "https://github.com/sharkdp/bat"
  },
  {
    "Name": "batcat.exe",
    "Size": "6.32 MB",
    "ModTime": "2024-05-17T23:42:03.352782000Z",
    "Source": "https://bin.ajam.dev/x64_Windows/batcat.exe",
    "B3SUM": "ffc7ddf867f641ab9d8646e863e3883e280d0c8c8821aa21894fcd14695a27ce",
    "SHA256": "71301ebe7945c231a8778730fd0d21633925d949475a7247e57154ec65a6c7a4",
    "Repo": "https://github.com/sharkdp/bat"
  },
  {
    "Name": "botsay.exe",
    "Size": "1.7 MB",
    "ModTime": "2024-05-17T23:42:04.290279200Z",
    "Source": "https://bin.ajam.dev/x64_Windows/botsay.exe",
    "B3SUM": "387aba6264960be05d175315a940ab8256c945d915dc92440b8ec90b60a1e4e1",
    "SHA256": "faa7830a32abe68f48b5bc9035fbec23e84799161120db6e452be42953d9e3a0",
    "Repo": "https://github.com/xyproto/botsay"
  },
  {
    "Name": "brook.exe",
    "Size": "20.63 MB",
    "ModTime": "2024-05-17T23:42:05.542206300Z",
    "Source": "https://bin.ajam.dev/x64_Windows/brook.exe",
    "B3SUM": "75793398b19c4a52c923a0baeeee9cc57b3ac7d86633abf0cbdb9bdb4379810e",
    "SHA256": "d3e91f53c0a2b36884bfe88a940ebeaece256cab6c61fa4de230b76843cfbab4",
    "Repo": "https://github.com/txthinking/brook"
  },
  {
    "Name": "brook_windows_amd64.exe",
    "Size": "20.63 MB",
    "ModTime": "2024-05-11T18:00:15.387227700Z",
    "Source": "https://bin.ajam.dev/x64_Windows/brook_windows_amd64.exe",
    "B3SUM": null,
    "SHA256": null,
    "Repo": null
  },
  {
    "Name": "brutespray.exe",
    "Size": "25.75 MB",
    "ModTime": "2024-05-17T23:42:06.605339300Z",
    "Source": "https://bin.ajam.dev/x64_Windows/brutespray.exe",
    "B3SUM": "da63a0561ca867036869ffb808ed77df910736e070a8a6326ace1daa753ae04b",
    "SHA256": "f82ffc3f6f12db9c05c558c71f75b2bc0f75926f0ec6920598a93e274b05e54a",
    "Repo": "https://github.com/x90skysn3k/brutespray"
  },
  {
    "Name": "busybox-unicode.exe",
    "Size": "666.11 kB",
    "ModTime": "2024-05-17T23:42:07.277222300Z",
    "Source": "https://bin.ajam.dev/x64_Windows/busybox-unicode.exe",
    "B3SUM": null,
    "SHA256": null,
    "Repo": null
  },
  {
    "Name": "busybox.exe",
    "Size": "659.97 kB",
    "ModTime": "2024-05-17T23:42:08.277756900Z",
    "Source": "https://bin.ajam.dev/x64_Windows/busybox.exe",
    "B3SUM": null,
    "SHA256": null,
    "Repo": null
  },
  {
    "Name": "cat.exe",
    "Size": "861.7 kB",
    "ModTime": "2024-05-17T23:42:09.294128400Z",
    "Source": "https://bin.ajam.dev/x64_Windows/cat.exe",
    "B3SUM": "4bbb278d30d4aa5dde29cf867b9593b5725551bec9d43b73eca5067482174e48",
    "SHA256": "2268c4d54d0899069f644a182c16b28d572666512e77e83a6bf5f9e7561bd3c5",
    "Repo": "https://github.com/uutils/coreutils"
  },
  {
    "Name": "certstream.exe",
    "Size": "4.86 MB",
    "ModTime": "2024-04-27T10:42:09.656277800Z",
    "Source": "https://bin.ajam.dev/x64_Windows/certstream.exe",
    "B3SUM": null,
    "SHA256": null,
    "Repo": null
  },
  {
    "Name": "cheat.exe",
    "Size": "11.57 MB",
    "ModTime": "2024-05-17T23:42:10.424086900Z",
    "Source": "https://bin.ajam.dev/x64_Windows/cheat.exe",
    "B3SUM": "1ad722f9d271cbd73f6f60d889090cff41684d38fecdda9d1edd327ded0c18d7",
    "SHA256": "f0a57278486d9388cef0fae4c147bf85b989c87588385f488753032a89646785",
    "Repo": "https://github.com/cheat/cheat"
  },
  {
    "Name": "cksum.exe",
    "Size": "1.03 MB",
    "ModTime": "2024-05-17T23:42:11.283949800Z",
    "Source": "https://bin.ajam.dev/x64_Windows/cksum.exe",
    "B3SUM": "73b19048c9d8285d5d397ddfc10421ce5aebbd42373f1827a89081e73e0c387e",
    "SHA256": "2b5760d2186c26e92716b827416381d104a2b5a2fd7b91d33f00714f16df80fa",
    "Repo": "https://github.com/uutils/coreutils"
  },
  {
    "Name": "cloudflared.exe",
    "Size": "27.01 MB",
    "ModTime": "2024-05-17T23:42:12.629367700Z",
    "Source": "https://bin.ajam.dev/x64_Windows/cloudflared.exe",
    "B3SUM": "81f1f5a241b5ad6bb7af31b53c4884185ed1817c202462020e475d2cad095a3d",
    "SHA256": "e80137b5a1250680f154c51fc70e6c212e721a9be14616a15a3d295bc2c20970",
    "Repo": "https://github.com/cloudflare/cloudflared"
  },
  {
    "Name": "comm.exe",
    "Size": "842.75 kB",
    "ModTime": "2024-05-17T23:42:13.285616500Z",
    "Source": "https://bin.ajam.dev/x64_Windows/comm.exe",
    "B3SUM": "17fa60ff7b2375c55f6650a85282d81381dbdd900364c1bf358da711197b9b34",
    "SHA256": "91a1f94733884cacdce4023abbe89a59908e8ed78496f9b23cc5d38d3277cd4a",
    "Repo": "https://github.com/uutils/coreutils"
  },
  {
    "Name": "coreutils-rs.exe",
    "Size": "9.62 MB",
    "ModTime": "2024-05-17T23:42:14.395543900Z",
    "Source": "https://bin.ajam.dev/x64_Windows/coreutils-rs.exe",
    "B3SUM": "51a549131826197e59f7bd76cac2bf6be194e63fc6c328e1e9d985f1e42a1b46",
    "SHA256": "b0fe5a5267b78fce7ddd89d98a4afcda62ff8159788768fc25aac072ba13a9fe",
    "Repo": "https://github.com/uutils/coreutils"
  },
  {
    "Name": "coreutils.exe",
    "Size": "9.62 MB",
    "ModTime": "2024-05-17T23:42:15.396255700Z",
    "Source": "https://bin.ajam.dev/x64_Windows/coreutils.exe",
    "B3SUM": "223380afa6d18f2dbb0ea7259cd068f7fda33a6af138cb7d377bc7873f12abd5",
    "SHA256": "eb0f89ed17776efcc6e9e6b2762fee408c32883c1d8b28aff5f2c6e403e7a4c8",
    "Repo": "https://github.com/uutils/coreutils"
  },
  {
    "Name": "cp.exe",
    "Size": "1.29 MB",
    "ModTime": "2024-05-17T23:42:16.286923300Z",
    "Source": "https://bin.ajam.dev/x64_Windows/cp.exe",
    "B3SUM": "560ab9f9137cc698a19388c9b83aafdc34b20761fc3ec912221a12f654f277c4",
    "SHA256": "9c40c808690fcf5ff8750f0d2904134399510541922aadb235fe042fdc89af25",
    "Repo": "https://github.com/uutils/coreutils"
  },
  {
    "Name": "croc.exe",
    "Size": "8.63 MB",
    "ModTime": "2024-05-17T23:42:17.396381900Z",
    "Source": "https://bin.ajam.dev/x64_Windows/croc.exe",
    "B3SUM": "fa7ce66c49d75cde4bbe825b6e7618ac76204c5bdce94d4e5ce4b444ac1ea904",
    "SHA256": "5589ff866ea02952a06e0645dd5bbe39777a65c607f9e19debd10d02b49b845b",
    "Repo": "https://github.com/schollz/croc"
  },
  {
    "Name": "csplit.exe",
    "Size": "2.32 MB",
    "ModTime": "2024-05-17T23:42:18.302852300Z",
    "Source": "https://bin.ajam.dev/x64_Windows/csplit.exe",
    "B3SUM": "7114f0c6a485d821c2c3c9db12a743caec57ae30f4f11a5ebe49d6db4af74552",
    "SHA256": "48865d07014f6266f196e0dee54face1eacb3d684d517f2f0b87d0739c86dda0",
    "Repo": "https://github.com/uutils/coreutils"
  },
  {
    "Name": "curl.exe",
    "Size": "7.46 MB",
    "ModTime": "2024-05-17T23:42:19.381278500Z",
    "Source": "https://bin.ajam.dev/x64_Windows/curl.exe",
    "B3SUM": "0edca09c1870e65b70043a84d3be9afcfbb9962ad750233b592d115fbcb2c1d6",
    "SHA256": "9b4410d866d3ed6db9815dc47e5f6930dc8356ce55f637a0117fa9adcff6bdf6",
    "Repo": "https://github.com/stunnel/static-curl"
  },
  {
    "Name": "cut.exe",
    "Size": "909.82 kB",
    "ModTime": "2024-05-17T23:42:20.287649200Z",
    "Source": "https://bin.ajam.dev/x64_Windows/cut.exe",
    "B3SUM": "887ebcbdea41c40c2735f63f42721efa9dccfb68ead382b8ead607ec9bf51417",
    "SHA256": "e67504effc9dc82057e8cdac4646ac5ea5db6933b71d7f41585e32baf6c4f605",
    "Repo": "https://github.com/uutils/coreutils"
  },
  {
    "Name": "cutlines.exe",
    "Size": "1.96 MB",
    "ModTime": "2024-05-17T23:42:21.303568700Z",
    "Source": "https://bin.ajam.dev/x64_Windows/cutlines.exe",
    "B3SUM": "254d4e0f6cefecc59a8f97e28f334866c140b5b194475ce696541f36485f3dc4",
    "SHA256": "fdce81c0ea36542c3c43a0aaa0cf2dc463f08b22be54579c935ac6cb802707d3",
    "Repo": "hhttps://github.com/Azathothas/Arsenal"
  },
  {
    "Name": "date.exe",
    "Size": "2.38 MB",
    "ModTime": "2024-05-17T23:42:22.319935100Z",
    "Source": "https://bin.ajam.dev/x64_Windows/date.exe",
    "B3SUM": "bcb445cc10d75f08a8c559d87f85352f3610c55e0aa40f3a315ee17e5cd971e1",
    "SHA256": "6127beb32f1799537aab9c2dc992a3c367f4470f1af59e4abf8aa0da855203ae",
    "Repo": "https://github.com/uutils/coreutils"
  },
  {
    "Name": "dbbench.exe",
    "Size": "30 MB",
    "ModTime": "2024-05-17T23:42:23.664530200Z",
    "Source": "https://bin.ajam.dev/x64_Windows/dbbench.exe",
    "B3SUM": "c4ce0d53a74ec062e012d5cda7aa94531de1f1d921d2b1a003d1468cd6db3395",
    "SHA256": "aee35148a019ad70a144e6174ffd7b953bb5c516c5983d446f9bbd0f141f35f7",
    "Repo": "https://github.com/sj14/dbbench"
  },
  {
    "Name": "dd.exe",
    "Size": "1.02 MB",
    "ModTime": "2024-05-17T23:42:24.289532400Z",
    "Source": "https://bin.ajam.dev/x64_Windows/dd.exe",
    "B3SUM": "6c2122bb2e3e05132447acd79ce60188eabfba7544222e548c659591cd52e1a0",
    "SHA256": "46c72e828e6b0b8bf725b115bd8218a635f89817866f49309d0a71eee599c6a2",
    "Repo": "https://github.com/uutils/coreutils"
  },
  {
    "Name": "ddns-go.exe",
    "Size": "9.47 MB",
    "ModTime": "2024-05-17T23:42:25.399218900Z",
    "Source": "https://bin.ajam.dev/x64_Windows/ddns-go.exe",
    "B3SUM": "7105ac6e9af42956f54477e51ea1d92d9b099fdd8823e48803bb147eba1c6854",
    "SHA256": "7e97705e0ce91abaaef24458169f86df6028c0fc2463ac9900fb82ef54f3fbd7",
    "Repo": "https://github.com/jeessy2/ddns-go"
  },
  {
    "Name": "deprun.exe",
    "Size": "3.06 MB",
    "ModTime": "2024-05-17T23:42:26.321185200Z",
    "Source": "https://bin.ajam.dev/x64_Windows/deprun.exe",
    "B3SUM": "936138d8ad1a63a76610626b2752513a5a3fa0be4bbdd2378c8f26f61d4bcabd",
    "SHA256": "c7607b48f304cb2ffae61151021af20921f4d450485440ceec025a90c9ebcee5",
    "Repo": "https://github.com/marcoesposito1988/dependency_runner"
  },
  {
    "Name": "df.exe",
    "Size": "962.56 kB",
    "ModTime": "2024-05-17T23:42:27.290729000Z",
    "Source": "https://bin.ajam.dev/x64_Windows/df.exe",
    "B3SUM": "556def5d373bab2acca0aaae4439861d6d385f936bdebb4c1d4be01d2d7cb11a",
    "SHA256": "9afd07e105d0313dcd7a587447658e059f5a0797a964d5b9331aff1fda8eb30f",
    "Repo": "https://github.com/uutils/coreutils"
  },
  {
    "Name": "dir.exe",
    "Size": "1.25 MB",
    "ModTime": "2024-05-17T23:42:28.291079900Z",
    "Source": "https://bin.ajam.dev/x64_Windows/dir.exe",
    "B3SUM": "4914ac37fec23050411a1edae9181b5590ddde8f2e32ac2cb51eabb1caad8647",
    "SHA256": "cfa9bcbd3b64653ba6dd7300c5af59ecbef4ef580d4bf1d25d4be79d58a12877",
    "Repo": "https://github.com/uutils/coreutils"
  },
  {
    "Name": "dircolors.exe",
    "Size": "901.12 kB",
    "ModTime": "2024-05-17T23:42:29.291763700Z",
    "Source": "https://bin.ajam.dev/x64_Windows/dircolors.exe",
    "B3SUM": "492911d8f36ea4d10c89786799cdc6a974cd262d02e456228e47d552afbeb315",
    "SHA256": "e908c3e5e7b863b1fba837647f00427bbeba9fc6ae451f70b18837eb3dd1fb87",
    "Repo": "https://github.com/uutils/coreutils"
  },
  {
    "Name": "dirname.exe",
    "Size": "816.64 kB",
    "ModTime": "2024-05-17T23:42:30.291953500Z",
    "Source": "https://bin.ajam.dev/x64_Windows/dirname.exe",
    "B3SUM": "3dc4c846238b6db8c69b050badcc7a101b9ee38bd9ff5e31ffacae09281d7b5f",
    "SHA256": "868ab489339436dad28a2a232e33562ebf492a8c695d5c212a5f2a74efb414be",
    "Repo": "https://github.com/uutils/coreutils"
  },
  {
    "Name": "du.exe",
    "Size": "1.12 MB",
    "ModTime": "2024-05-17T23:42:31.292464500Z",
    "Source": "https://bin.ajam.dev/x64_Windows/du.exe",
    "B3SUM": "d49fd4a16e72269ec0aa398c072fd1db4499635a9264144bcb46535a37283e51",
    "SHA256": "078c053072634a2a733aaa4f423c78b9b967aad7e0a63faaffda5b22d347793e",
    "Repo": "https://github.com/uutils/coreutils"
  },
  {
    "Name": "dua.exe",
    "Size": "1.56 MB",
    "ModTime": "2024-05-17T23:42:32.293530600Z",
    "Source": "https://bin.ajam.dev/x64_Windows/dua.exe",
    "B3SUM": "ab445eb08386c601ed61cf5db24c2cab6e13775f00d29c0c3a77f0da5274cbaf",
    "SHA256": "684afc040ae9fc839c807214ccefdace79d8b50b0bc8dd7df024a927c2b4e5ce",
    "Repo": "https://github.com/Byron/dua-cli"
  },
  {
    "Name": "dufs.exe",
    "Size": "3.68 MB",
    "ModTime": "2024-05-17T23:42:33.340747700Z",
    "Source": "https://bin.ajam.dev/x64_Windows/dufs.exe",
    "B3SUM": "52a11fc2ba7e232eb43f14ee32ce9b25a457bd5c88b4d3ba11005d01f5ab655a",
    "SHA256": "4de96119e0868d31343919f055e618a5eae8f7da0bc875b1e37c4e285a68b2b9",
    "Repo": "https://github.com/sigoden/dufs"
  },
  {
    "Name": "dust.exe",
    "Size": "2.79 MB",
    "ModTime": "2024-05-17T23:42:34.325237600Z",
    "Source": "https://bin.ajam.dev/x64_Windows/dust.exe",
    "B3SUM": "2440f314758216e55ae342f9ad35abd425ee1fc9e8ddf8f8eb03621dda1af264",
    "SHA256": "c9decd787e2c411a48df2126d0c516db1679912f71f9bace10536692e6a4596d",
    "Repo": "https://github.com/bootandy/dust"
  },
  {
    "Name": "echo.exe",
    "Size": "815.1 kB",
    "ModTime": "2024-05-17T23:42:35.295024200Z",
    "Source": "https://bin.ajam.dev/x64_Windows/echo.exe",
    "B3SUM": "6329bf7898ccb177a242acb05fea2538494a92425b8f4c18f35e3bc28f8dafeb",
    "SHA256": "631c93e1b73836131ac0eb7722ecfe04b9e6d7673648f34c187bec73538a46e9",
    "Repo": "https://github.com/uutils/coreutils"
  },
  {
    "Name": "eget.exe",
    "Size": "6.94 MB",
    "ModTime": "2024-05-17T23:42:36.376524100Z",
    "Source": "https://bin.ajam.dev/x64_Windows/eget.exe",
    "B3SUM": "25eb53d3a21c9955bce08be7ab4a8d086d6dd69d428a6d399df0b005e09838d9",
    "SHA256": "269012a88f4beee737fe220579d4b11ede572fdf2b96331989a4c41b38c35d61",
    "Repo": "https://github.com/zyedidia/eget"
  },
  {
    "Name": "ein.exe",
    "Size": "9.17 MB",
    "ModTime": "2024-05-17T23:42:37.408445400Z",
    "Source": "https://bin.ajam.dev/x64_Windows/ein.exe",
    "B3SUM": null,
    "SHA256": null,
    "Repo": null
  },
  {
    "Name": "env.exe",
    "Size": "1.02 MB",
    "ModTime": "2024-05-17T23:42:38.299575700Z",
    "Source": "https://bin.ajam.dev/x64_Windows/env.exe",
    "B3SUM": "6990e7b03fbcd0081e5042aa46f42acff30d6d4261fe41e466c39779778d70d4",
    "SHA256": "c3aa7579a27f41e0b1f6d5b219687e8d699c243a159950a52a6e981ff2a5b820",
    "Repo": "https://github.com/uutils/coreutils"
  },
  {
    "Name": "err.exe",
    "Size": "2.29 MB",
    "ModTime": "2024-05-17T23:42:39.315910800Z",
    "Source": "https://bin.ajam.dev/x64_Windows/err.exe",
    "B3SUM": "aa36a59d96308105033e78ea7a6d90e63f3f1ece80538357ff247cbe53c2d8b9",
    "SHA256": "eff565e57d95d33abd4535bbb2d4e8c987169c14f575f25ba0fccee27ea354a5",
    "Repo": "https://www.microsoft.com/en-us/download/details.aspx?id=100432"
  },
  {
    "Name": "expand.exe",
    "Size": "872.96 kB",
    "ModTime": "2024-05-17T23:42:40.300477500Z",
    "Source": "https://bin.ajam.dev/x64_Windows/expand.exe",
    "B3SUM": "b28928893f656590ee187deb22ab0673aac7db1edeadc040e93e5e4f3ef781c3",
    "SHA256": "48f4f012d6fc3dba35e161724eefcc758f5a0f09204ce34519d9873cebbfacfd",
    "Repo": "https://github.com/uutils/coreutils"
  },
  {
    "Name": "expr.exe",
    "Size": "1.43 MB",
    "ModTime": "2024-05-17T23:42:41.301265500Z",
    "Source": "https://bin.ajam.dev/x64_Windows/expr.exe",
    "B3SUM": "987e5fa4fb889ef4dd600aef7c963e60c7ddeb5bc0cd191e5468b21725333544",
    "SHA256": "0390f85edc2bbe574b8c0d1efbc1db9d7ec156fb96659261431217e4b772000d",
    "Repo": "https://github.com/uutils/coreutils"
  },
  {
    "Name": "factor.exe",
    "Size": "1.23 MB",
    "ModTime": "2024-05-17T23:42:42.302292900Z",
    "Source": "https://bin.ajam.dev/x64_Windows/factor.exe",
    "B3SUM": "9293b131f3583172e1035f051582d23feffb78af4899ac7a4369c86b8968b92b",
    "SHA256": "bd9d9f9b222ab41531dfabe1aa0ee79c9d416c08327a1972b4b59907d170443b",
    "Repo": "https://github.com/uutils/coreutils"
  },
  {
    "Name": "false.exe",
    "Size": "758.27 kB",
    "ModTime": "2024-05-17T23:42:43.302548800Z",
    "Source": "https://bin.ajam.dev/x64_Windows/false.exe",
    "B3SUM": "400e102defd7b61a5285822587810ad4e95d19ec66ce428abe365909a346d7da",
    "SHA256": "f3f4c9a761bce50aa708a48dbe082a6e2c143f3f62b8d4c511ec6079fe66839a",
    "Repo": "https://github.com/uutils/coreutils"
  },
  {
    "Name": "fastfetch.exe",
    "Size": "1.35 MB",
    "ModTime": "2024-05-17T23:42:44.302682400Z",
    "Source": "https://bin.ajam.dev/x64_Windows/fastfetch.exe",
    "B3SUM": "f946569e69407c6f3db3f7402b595ca20298e214312615b728428d0d622252eb",
    "SHA256": "e0c89c392fc747241aa3f52d973444e3d4d8436a311aadcef7d9ca3ea4aea26d",
    "Repo": "https://github.com/fastfetch-cli/fastfetch"
  },
  {
    "Name": "ffmpeg.exe",
    "Size": "141.54 MB",
    "ModTime": "2024-05-17T23:42:47.429000000Z",
    "Source": "https://bin.ajam.dev/x64_Windows/ffmpeg.exe",
    "B3SUM": "aa1f9107c0a068b42b8d8bef937b66f49dde97661d69e51d0f63802206675901",
    "SHA256": "505d7ded0649f47fad75b6f062e0de42fcdab89d8b56e9cd1935e6cd56c14549",
    "Repo": "https://ffmpeg.org"
  },
  {
    "Name": "ffplay.exe",
    "Size": "141.36 MB",
    "ModTime": "2024-05-17T23:42:50.399022600Z",
    "Source": "https://bin.ajam.dev/x64_Windows/ffplay.exe",
    "B3SUM": null,
    "SHA256": null,
    "Repo": null
  },
  {
    "Name": "ffprobe.exe",
    "Size": "141.37 MB",
    "ModTime": "2024-05-17T23:42:53.401316900Z",
    "Source": "https://bin.ajam.dev/x64_Windows/ffprobe.exe",
    "B3SUM": "cdd6c7978a6cdf58347dd6b743166c3ce8a848cb1e420923989c9d2fe29849a6",
    "SHA256": "087c4362e78d1d0b7d6e33e3b855c33132eff5671ce393218e2514c60db50286",
    "Repo": "https://ffmpeg.org"
  },
  {
    "Name": "find-rs.exe",
    "Size": "2.13 MB",
    "ModTime": "2024-05-17T23:42:54.323261000Z",
    "Source": "https://bin.ajam.dev/x64_Windows/find-rs.exe",
    "B3SUM": "ef3a4414ab6978627b58b29d748b0933f44fbab6f8c1aceff588fd9b743ee60d",
    "SHA256": "d249b0f02bc0254aab40561406d756d76451daea1365b77000ec352e49c30b61",
    "Repo": "https://github.com/uutils/findutils"
  },
  {
    "Name": "find.exe",
    "Size": "2.13 MB",
    "ModTime": "2024-05-17T23:42:55.323714500Z",
    "Source": "https://bin.ajam.dev/x64_Windows/find.exe",
    "B3SUM": "14cefef73348cd397452def944190b79ee1eb9edcdfc75ac9d1d2e930df81d12",
    "SHA256": "a6fb3cd11e6ab67130865e12c8ba9f2fbcc1228acb09d5251b5268a51fb1fbd7",
    "Repo": "https://github.com/uutils/findutils"
  },
  {
    "Name": "flashfetch.exe",
    "Size": "1.19 MB",
    "ModTime": "2024-05-17T23:42:56.308191100Z",
    "Source": "https://bin.ajam.dev/x64_Windows/flashfetch.exe",
    "B3SUM": "67f916e0595ea57d83ab10494a1f470c317d74215b2f3e5b7a5f23d25cc08c0f",
    "SHA256": "90febdf643186214becb3c72f79063ea72a2dafde865ed81819be2763354147a",
    "Repo": "https://github.com/fastfetch-cli/fastfetch"
  },
  {
    "Name": "fmt.exe",
    "Size": "903.68 kB",
    "ModTime": "2024-05-17T23:42:57.308673400Z",
    "Source": "https://bin.ajam.dev/x64_Windows/fmt.exe",
    "B3SUM": "9c8e322af0c87b041a7cd6b17a4917b0d4e13eddb39349344b2ab57e3ef1db7a",
    "SHA256": "5a3eb6db9d36060f9815a67b8ead5d3a755201eacc6da5b416bc6a0f8f20e72c",
    "Repo": "https://github.com/uutils/coreutils"
  },
  {
    "Name": "fold.exe",
    "Size": "859.65 kB",
    "ModTime": "2024-05-17T23:42:58.308979800Z",
    "Source": "https://bin.ajam.dev/x64_Windows/fold.exe",
    "B3SUM": "fb4934edd6c00305aede85d82ea146efb672785cb711a8fca8d241aac6664904",
    "SHA256": "88e414b7ea4aca4926ead684d5169f068623b7bf50cc8dfd8350f87c3737eeb9",
    "Repo": "https://github.com/uutils/coreutils"
  },
  {
    "Name": "gdu.exe",
    "Size": "14.23 MB",
    "ModTime": "2024-05-17T23:42:59.481188600Z",
    "Source": "https://bin.ajam.dev/x64_Windows/gdu.exe",
    "B3SUM": "f4fc3b8896eeb26256b251b6445965117df3154e78b75796edf9df3d897fe0d5",
    "SHA256": "950acd94e6f4825dbf585cf93c745b52256b6e10ce17c1d729eb6afa64db3d3f",
    "Repo": "https://github.com/dundee/gdu"
  },
  {
    "Name": "geodns.exe",
    "Size": "2.37 MB",
    "ModTime": "2024-05-17T23:43:00.356231000Z",
    "Source": "https://bin.ajam.dev/x64_Windows/geodns.exe",
    "B3SUM": "d18c65bea45058258be4f4356e44cb358a5453c3cb1e75d690bc3fc38c625c4e",
    "SHA256": "1a7825f11da7e1e9cc3062e0bbf37a9a9ea784e1478c2b8f8d8b91ea415ef48f",
    "Repo": "https://gitlab.com/shodan-public/geonet-rs"
  },
  {
    "Name": "geoping.exe",
    "Size": "2.37 MB",
    "ModTime": "2024-05-17T23:43:01.340927600Z",
    "Source": "https://bin.ajam.dev/x64_Windows/geoping.exe",
    "B3SUM": "e2375e486f85d90883742b8ebfbe15546defd87e7406a3c05909467a034b6a29",
    "SHA256": "bcc6469a8aed186481eef96f2e4385003e6dafd04abc3486ec4a533fbbe84227",
    "Repo": "https://gitlab.com/shodan-public/geonet-rs"
  },
  {
    "Name": "gix.exe",
    "Size": "18.42 MB",
    "ModTime": "2024-05-17T23:43:02.560539200Z",
    "Source": "https://bin.ajam.dev/x64_Windows/gix.exe",
    "B3SUM": null,
    "SHA256": null,
    "Repo": null
  },
  {
    "Name": "hashsum.exe",
    "Size": "2.48 MB",
    "ModTime": "2024-05-17T23:43:03.357997700Z",
    "Source": "https://bin.ajam.dev/x64_Windows/hashsum.exe",
    "B3SUM": "afc89305f22ab734222ce0b2679166c11e5a2da2ecc745653d5f3887b554fa80",
    "SHA256": "029eedb6933ca236b93d5985df5bb8b54b62bd1ab8e4a938a5003079e68759fd",
    "Repo": "https://github.com/uutils/coreutils"
  },
  {
    "Name": "head.exe",
    "Size": "899.07 kB",
    "ModTime": "2024-05-17T23:43:04.332300600Z",
    "Source": "https://bin.ajam.dev/x64_Windows/head.exe",
    "B3SUM": "b89e840249167414b467832d520c448ef3757235a44b7dcb90fc38de1a20f3e3",
    "SHA256": "84e7300ed2a7af438e8c4b9ec9ac882fcba427a83d93e2cc5245e42e639cfa0a",
    "Repo": "https://github.com/uutils/coreutils"
  },
  {
    "Name": "hostname.exe",
    "Size": "844.29 kB",
    "ModTime": "2024-05-17T23:43:05.333041200Z",
    "Source": "https://bin.ajam.dev/x64_Windows/hostname.exe",
    "B3SUM": "ad53b5ca6311f41bb7955f9792077e4f107398532e6e4346396587861db24e92",
    "SHA256": "4ca70146be02a41f6e35df3ed91300674921ef8f5277ceba9b84546e237cc958",
    "Repo": "https://github.com/uutils/coreutils"
  },
  {
    "Name": "hyperfine.exe",
    "Size": "1.33 MB",
    "ModTime": "2024-05-17T23:43:06.333260600Z",
    "Source": "https://bin.ajam.dev/x64_Windows/hyperfine.exe",
    "B3SUM": "77dbb2ac3be30c9fa59582162de4b7ee204b75853bcbb9c61f11106d3833dfb0",
    "SHA256": "ed5c9379c3457e49e6711612ca7e30335683d68d47cb7e1d18d39a56d6a7981d",
    "Repo": "https://github.com/sharkdp/hyperfine"
  },
  {
    "Name": "inscope.exe",
    "Size": "1.8 MB",
    "ModTime": "2024-05-17T23:43:07.349171700Z",
    "Source": "https://bin.ajam.dev/x64_Windows/inscope.exe",
    "B3SUM": "f420093900ecc272ef662feefacbba6e4c23eeda4fd21456e460f9b4173d2a7c",
    "SHA256": "776a346aebbe7bdc56c04a49fc832e48d4f21e9c0057ffdf88d2fe59c0aec631",
    "Repo": "hhttps://github.com/Azathothas/Arsenal"
  },
  {
    "Name": "iperf3.exe",
    "Size": "141.82 kB",
    "ModTime": "2024-05-17T23:43:08.318247400Z",
    "Source": "https://bin.ajam.dev/x64_Windows/iperf3.exe",
    "B3SUM": "6b7d55a2ef7af1291f4c8847563a70798e02cb95cfe08ab9c8ce9abdce3a57d3",
    "SHA256": "89517e8811e5a7738e2337fc680af60fa8c33fb7c875ac5c642786bd84280d79",
    "Repo": "https://github.com/userdocs/iperf3-static\nhttps://github.com/userdocs/iperf3-static"
  },
  {
    "Name": "join.exe",
    "Size": "913.92 kB",
    "ModTime": "2024-05-17T23:43:09.324098800Z",
    "Source": "https://bin.ajam.dev/x64_Windows/join.exe",
    "B3SUM": "6ad6569965cba780d8f2b48f0edd3d0a0995be0ddb6811f6aa045d2e2b4f5c5b",
    "SHA256": "e9bc6cba932bda8d4cffc35b90e8f8f20db0b0f283bd207040d5ade817097069",
    "Repo": "https://github.com/uutils/coreutils"
  },
  {
    "Name": "jq.exe",
    "Size": "985.09 kB",
    "ModTime": "2024-05-17T23:43:10.340563100Z",
    "Source": "https://bin.ajam.dev/x64_Windows/jq.exe",
    "B3SUM": "8de06b612581de9f8d704516e8f2fe0470bcab6ad589c0782dd1679726b78866",
    "SHA256": "7f978c6bf1ee8d5f1225b38a990487d3d0e1403247fbf87ad2a73b7457ef44fb",
    "Repo": "https://github.com/jqlang/jq"
  },
  {
    "Name": "jwt-cracker.exe",
    "Size": "1.91 MB",
    "ModTime": "2024-05-17T23:43:11.356591700Z",
    "Source": "https://bin.ajam.dev/x64_Windows/jwt-cracker.exe",
    "B3SUM": "ce1a018e9df3305fa22d82c8ce3627600e8d7eb9a22fe28e1b15a7c6ac4cd2f5",
    "SHA256": "c732f0d2e12b6fe71d4ab2f737f0f2ec275ecc4533feeb2d3ea836ff76c17858",
    "Repo": "https://github.com/Azathothas/jwt-cracker"
  },
  {
    "Name": "legba.exe",
    "Size": "22.23 MB",
    "ModTime": "2024-05-17T23:43:12.623580800Z",
    "Source": "https://bin.ajam.dev/x64_Windows/legba.exe",
    "B3SUM": "5f4d0d93084c9fc0af5b7042f62ae5d66d0e43aef710f239db0a1195af6ea552",
    "SHA256": "1a20b5e031e94d33448e5bb56bc49910518e16692550c1fef357112a877f48ef",
    "Repo": "https://github.com/evilsocket/legba"
  },
  {
    "Name": "link.exe",
    "Size": "829.95 kB",
    "ModTime": "2024-05-17T23:43:13.342374900Z",
    "Source": "https://bin.ajam.dev/x64_Windows/link.exe",
    "B3SUM": "d7e8b656375297f1ebfe1d9ecd5a33514fbb1af9987d2ce19ca5ee46436cff10",
    "SHA256": "29549a74e1c048fa32c693716d056e1be509404da55849b46e6f4008dfa005c6",
    "Repo": "https://github.com/uutils/coreutils"
  },
  {
    "Name": "ln.exe",
    "Size": "929.79 kB",
    "ModTime": "2024-05-17T23:43:14.348189800Z",
    "Source": "https://bin.ajam.dev/x64_Windows/ln.exe",
    "B3SUM": "f5f2fbb4a33ab6d22bb007199fc041be9411608a0a93d07ba3df2e4dda1157ef",
    "SHA256": "9ddfbc96f83ea67585699ffe10463d1ea0ba7412e6d846ab0deec7cc35802587",
    "Repo": "https://github.com/uutils/coreutils"
  },
  {
    "Name": "localxpose.exe",
    "Size": "23.85 MB",
    "ModTime": "2024-05-17T23:43:15.647384700Z",
    "Source": "https://bin.ajam.dev/x64_Windows/localxpose.exe",
    "B3SUM": null,
    "SHA256": null,
    "Repo": null
  },
  {
    "Name": "loclx.exe",
    "Size": "23.85 MB",
    "ModTime": "2024-05-17T23:43:16.647716000Z",
    "Source": "https://bin.ajam.dev/x64_Windows/loclx.exe",
    "B3SUM": null,
    "SHA256": null,
    "Repo": null
  },
  {
    "Name": "ls.exe",
    "Size": "1.27 MB",
    "ModTime": "2024-05-17T23:43:17.350837800Z",
    "Source": "https://bin.ajam.dev/x64_Windows/ls.exe",
    "B3SUM": "104f6416d69157a7804728391e2276a08d3a8fe14abb9c0d76b7667bce8b02c3",
    "SHA256": "58570675364319a85ca47fd408e016ed0eb529d7bba0ade5223d8a236ac87a0a",
    "Repo": "https://github.com/uutils/coreutils"
  },
  {
    "Name": "micro.exe",
    "Size": "11.88 MB",
    "ModTime": "2024-05-17T23:43:18.496694400Z",
    "Source": "https://bin.ajam.dev/x64_Windows/micro.exe",
    "B3SUM": "e16f701af908bd052108c3fef9d80360753522f6f2c6ea818994274da4e91254",
    "SHA256": "4f9af640af9114622f886161191a6c4346ad46cbbe98064ed4d8d6cd1c060b66",
    "Repo": "https://github.com/zyedidia/micro"
  },
  {
    "Name": "miniserve.exe",
    "Size": "1.9 MB",
    "ModTime": "2024-03-30T12:20:15.004750200Z",
    "Source": "https://bin.ajam.dev/x64_Windows/miniserve.exe",
    "B3SUM": "cd7cd96ee8095de0a0b6f83fee48c32bf8c2695ad5deb922177a5f1775aab676",
    "SHA256": "060705db94b7ea673486db72ffc54fbd5e3c898758f9a16575d636c78e95dffb",
    "Repo": "https://github.com/svenstaro/miniserve"
  },
  {
    "Name": "mkdir.exe",
    "Size": "839.68 kB",
    "ModTime": "2024-05-17T23:43:20.356866900Z",
    "Source": "https://bin.ajam.dev/x64_Windows/mkdir.exe",
    "B3SUM": "b3b995aac7e4da1c20c9412bd9370dd5ff147f690d95885fcc87820d37e4335c",
    "SHA256": "1db22ae84d46ab851f81cabed1d5732c0d7aec0ac971e98b11924ce8683c2dc7",
    "Repo": "https://github.com/uutils/coreutils"
  },
  {
    "Name": "mktemp.exe",
    "Size": "933.89 kB",
    "ModTime": "2024-05-17T23:43:21.357338000Z",
    "Source": "https://bin.ajam.dev/x64_Windows/mktemp.exe",
    "B3SUM": "7accb65e9f24263a59cfef560b695f6f926e8c5f90c1721a29041499b50ddb10",
    "SHA256": "24cac75ec4851755204af776efa3a1adaa7f40687f34f7f25689cbca60dcb73b",
    "Repo": "https://github.com/uutils/coreutils"
  },
  {
    "Name": "monolith.exe",
    "Size": "5.21 MB",
    "ModTime": "2024-05-17T23:43:22.420267600Z",
    "Source": "https://bin.ajam.dev/x64_Windows/monolith.exe",
    "B3SUM": "af3a8c4ee68e1e0848a2225f37e6cbe49b9ef7f1e6fbae79e32418df9721f961",
    "SHA256": "897d529cd1a4b9129035e22cf1b3e7e4f2ae65aec2816dcb5946b67ac0f7d64d",
    "Repo": "https://github.com/Y2Z/monolith"
  },
  {
    "Name": "more.exe",
    "Size": "988.16 kB",
    "ModTime": "2024-05-17T23:43:23.358571600Z",
    "Source": "https://bin.ajam.dev/x64_Windows/more.exe",
    "B3SUM": "9d3c41117c51eb31b89c3946a735666befc0e7040eadfaa05a954fc7d0802822",
    "SHA256": "78d777cec9535738277e2b14ba3267800f0e452ca6fa7f8113a313f2c2c1262b",
    "Repo": "https://github.com/uutils/coreutils"
  },
  {
    "Name": "mv.exe",
    "Size": "1.17 MB",
    "ModTime": "2024-05-17T23:43:24.363386600Z",
    "Source": "https://bin.ajam.dev/x64_Windows/mv.exe",
    "B3SUM": "fea202e549ac83551913d191b7d0f769526f3092c270546cabe1b969b2ae5306",
    "SHA256": "3c4e1268a121aa49562a839e19f542c11b43990b8ee407886ee7b4e7c17ff0bd",
    "Repo": "https://github.com/uutils/coreutils"
  },
  {
    "Name": "ngrok.exe",
    "Size": "29.52 MB",
    "ModTime": "2024-05-17T23:43:25.740793900Z",
    "Source": "https://bin.ajam.dev/x64_Windows/ngrok.exe",
    "B3SUM": null,
    "SHA256": null,
    "Repo": null
  },
  {
    "Name": "nl.exe",
    "Size": "2.28 MB",
    "ModTime": "2024-05-17T23:43:26.381427100Z",
    "Source": "https://bin.ajam.dev/x64_Windows/nl.exe",
    "B3SUM": "34f39a4444008169d35a978c1d285e33e52092b55df7b9f8cf3bb97e13ab21ca",
    "SHA256": "d48c66ab84d9538babefbf6162c61e9f3fe3491d91fe25eb1c8923b4f465974f",
    "Repo": "https://github.com/uutils/coreutils"
  },
  {
    "Name": "nproc.exe",
    "Size": "828.93 kB",
    "ModTime": "2024-05-17T23:43:27.366520800Z",
    "Source": "https://bin.ajam.dev/x64_Windows/nproc.exe",
    "B3SUM": "7e6b17606902a31402ce87d603438088df72bb2bcf5e4c3988165516a1121d7c",
    "SHA256": "e663026f132bfeaf229b687d929ece91c6ce94b9513431a231aa6ef33b8c09cf",
    "Repo": "https://github.com/uutils/coreutils"
  },
  {
    "Name": "numfmt.exe",
    "Size": "955.9 kB",
    "ModTime": "2024-05-17T23:43:28.367023800Z",
    "Source": "https://bin.ajam.dev/x64_Windows/numfmt.exe",
    "B3SUM": "e95e9e12049c1ab516a3a883557aae7c7e0f190b71473b7c1cb2e4714b074395",
    "SHA256": "fdab8c569c4ebcc8aded08ab31d46ed91ecc52b2724dfafe79bc6df243367f53",
    "Repo": "https://github.com/uutils/coreutils"
  },
  {
    "Name": "od.exe",
    "Size": "1 MB",
    "ModTime": "2024-05-17T23:43:29.367254400Z",
    "Source": "https://bin.ajam.dev/x64_Windows/od.exe",
    "B3SUM": "eec40a0aef3e31c660471e2722ec68603f100d16b004035a0f5453945ae8be87",
    "SHA256": "a8d61941e7ee1e653a959c6d3d42827beea42ac7af0f663f73fde67854840eaf",
    "Repo": "https://github.com/uutils/coreutils"
  },
  {
    "Name": "openssh.zip",
    "Size": "4.86 MB",
    "ModTime": "2024-04-05T23:44:01.744097900Z",
    "Source": "https://bin.ajam.dev/x64_Windows/openssh.zip",
    "B3SUM": null,
    "SHA256": null,
    "Repo": null
  },
  {
    "Name": "pandoc.exe",
    "Size": "159.3 MB",
    "ModTime": "2024-05-17T23:43:33.871870200Z",
    "Source": "https://bin.ajam.dev/x64_Windows/pandoc.exe",
    "B3SUM": "b3bdb281cc8ce7862557073bad29b95b6ae548b5602451ce122751e0966745ee",
    "SHA256": "e9389a6eb3cf83b1e438297f168c94ede7a2bbe870c77938b919a49bf182f4db",
    "Repo": "https://github.com/jgm/pandoc"
  },
  {
    "Name": "paste.exe",
    "Size": "835.07 kB",
    "ModTime": "2024-05-17T23:43:34.360685900Z",
    "Source": "https://bin.ajam.dev/x64_Windows/paste.exe",
    "B3SUM": "5ff6cecbe1df5351126bb9c6c2cd18dbbd228afe4ea81230edc7d456b2f19b3c",
    "SHA256": "3757354a050efc553f5a25b5704ee5af902f1558c4ad9bd30553e762baa55436",
    "Repo": "https://github.com/uutils/coreutils"
  },
  {
    "Name": "pdfcpu.exe",
    "Size": "11.55 MB",
    "ModTime": "2024-05-17T23:43:35.517382100Z",
    "Source": "https://bin.ajam.dev/x64_Windows/pdfcpu.exe",
    "B3SUM": "d4251a3e4a61700543b8994b8d39d5f42ef9f408da73b25d853d1cf2b2198ac8",
    "SHA256": "6de4f30c8b1fd2663128ecff49b15d2506d3d5bf477b05f2e62db79bedc4cd50",
    "Repo": "https://github.com/pdfcpu/pdfcpu"
  },
  {
    "Name": "pdfdetach.exe",
    "Size": "1.25 MB",
    "ModTime": "2024-05-17T23:43:36.376837600Z",
    "Source": "https://bin.ajam.dev/x64_Windows/pdfdetach.exe",
    "B3SUM": null,
    "SHA256": null,
    "Repo": null
  },
  {
    "Name": "pdffonts.exe",
    "Size": "1.27 MB",
    "ModTime": "2024-05-17T23:43:37.377113700Z",
    "Source": "https://bin.ajam.dev/x64_Windows/pdffonts.exe",
    "B3SUM": null,
    "SHA256": null,
    "Repo": null
  },
  {
    "Name": "pdfimages.exe",
    "Size": "1.33 MB",
    "ModTime": "2024-05-17T23:43:38.377492000Z",
    "Source": "https://bin.ajam.dev/x64_Windows/pdfimages.exe",
    "B3SUM": null,
    "SHA256": null,
    "Repo": null
  },
  {
    "Name": "pdfinfo.exe",
    "Size": "1.28 MB",
    "ModTime": "2024-05-17T23:43:39.383190500Z",
    "Source": "https://bin.ajam.dev/x64_Windows/pdfinfo.exe",
    "B3SUM": null,
    "SHA256": null,
    "Repo": null
  },
  {
    "Name": "pdftopng.exe",
    "Size": "2.23 MB",
    "ModTime": "2024-05-17T23:43:40.406574400Z",
    "Source": "https://bin.ajam.dev/x64_Windows/pdftopng.exe",
    "B3SUM": null,
    "SHA256": null,
    "Repo": null
  },
  {
    "Name": "pdftoppm.exe",
    "Size": "2.15 MB",
    "ModTime": "2024-05-17T23:43:41.406672900Z",
    "Source": "https://bin.ajam.dev/x64_Windows/pdftoppm.exe",
    "B3SUM": null,
    "SHA256": null,
    "Repo": null
  },
  {
    "Name": "pdftops.exe",
    "Size": "2.34 MB",
    "ModTime": "2024-05-17T23:43:42.407509500Z",
    "Source": "https://bin.ajam.dev/x64_Windows/pdftops.exe",
    "B3SUM": null,
    "SHA256": null,
    "Repo": null
  },
  {
    "Name": "pdftotext.exe",
    "Size": "1.39 MB",
    "ModTime": "2024-05-17T23:43:43.392734800Z",
    "Source": "https://bin.ajam.dev/x64_Windows/pdftotext.exe",
    "B3SUM": null,
    "SHA256": null,
    "Repo": null
  },
  {
    "Name": "pgrok.exe",
    "Size": "10.17 MB",
    "ModTime": "2024-05-17T23:43:44.518246500Z",
    "Source": "https://bin.ajam.dev/x64_Windows/pgrok.exe",
    "B3SUM": "32f954ee7c7ae9885aca98cb390d2872efd8fc63308152fc21bf2043e509ee02",
    "SHA256": "92b46983ffec05ec1fb35e2509019f6cd56186b8c5c77090021f6f7855cc5503",
    "Repo": "https://github.com/pgrok/pgrok"
  },
  {
    "Name": "pgrokd.exe",
    "Size": "15.67 MB",
    "ModTime": "2024-05-17T23:43:45.581749200Z",
    "Source": "https://bin.ajam.dev/x64_Windows/pgrokd.exe",
    "B3SUM": "10433b7af88457ee96e77dcfbd7a1c2c2195e9f99d488e0bd7aa2533eef82cf7",
    "SHA256": "7e4d3688c508d67c845a8dd171c7634eb50c2d99b4832e33a6de0dddf44a5532",
    "Repo": "https://github.com/pgrok/pgrok"
  },
  {
    "Name": "pingmole.exe",
    "Size": "3.8 MB",
    "ModTime": "2024-05-17T23:43:46.441663300Z",
    "Source": "https://bin.ajam.dev/x64_Windows/pingmole.exe",
    "B3SUM": "907f1ea6948570ee22f755b50237ff8700be937a3d9308be62136eff23226d41",
    "SHA256": "7f216c8c37ce44bc7f7b0150ef000b6e8ab2d7e30414bbc47d6c47c307665308",
    "Repo": "https://github.com/norskeld/pingmole"
  },
  {
    "Name": "pingtunnel.exe",
    "Size": "8.98 MB",
    "ModTime": "2024-05-17T23:43:47.504898400Z",
    "Source": "https://bin.ajam.dev/x64_Windows/pingtunnel.exe",
    "B3SUM": "6a35dab1d1f7b3a5064dd2f89ba5ecf327c2963c845bc75ab505531350587ba0",
    "SHA256": "dfe9eb57b168a1fad143cec0f780d48e3f84619012244141df9dad6e16353a47",
    "Repo": "https://github.com/esrrhs/pingtunnel"
  },
  {
    "Name": "pr.exe",
    "Size": "2.4 MB",
    "ModTime": "2024-05-17T23:43:48.411251300Z",
    "Source": "https://bin.ajam.dev/x64_Windows/pr.exe",
    "B3SUM": "c447e926ed11cacbf39f425d297418aadf7069ffce120878165deb3d8075b0e9",
    "SHA256": "351ac530e9fdc04e809868ff18dd134566fbb22e35a685e3acbf458fa42a5a46",
    "Repo": "https://github.com/uutils/coreutils"
  },
  {
    "Name": "printenv.exe",
    "Size": "803.84 kB",
    "ModTime": "2024-05-17T23:43:49.395883900Z",
    "Source": "https://bin.ajam.dev/x64_Windows/printenv.exe",
    "B3SUM": "6dbd2bf15dbe4003e95d3b1a9b304c2f5b1c727ee2457a3289848243bb8cbed8",
    "SHA256": "da56c2a5ce845f0cff4517d50210b96be95b370cead3fb4b88844103b85e251e",
    "Repo": "https://github.com/uutils/coreutils"
  },
  {
    "Name": "printf.exe",
    "Size": "914.94 kB",
    "ModTime": "2024-05-17T23:43:50.396474200Z",
    "Source": "https://bin.ajam.dev/x64_Windows/printf.exe",
    "B3SUM": "e956e277bc592b63218a65e502f5d88b0272445b7d93db4209ec54ae5d4229cc",
    "SHA256": "a115e1e2a37f47e8c51d79af3dd983d52add2447f41d4924b8eacd623ae1dd93",
    "Repo": "https://github.com/uutils/coreutils"
  },
  {
    "Name": "ptx.exe",
    "Size": "2.37 MB",
    "ModTime": "2024-05-17T23:43:51.412649700Z",
    "Source": "https://bin.ajam.dev/x64_Windows/ptx.exe",
    "B3SUM": "f2b7e5abaf32326dba7efc376d6be138bfc9803ab53d62fab63bab23c3554969",
    "SHA256": "765bd5cfeabef86247731aa6237848ed6ae2aa08309e3e228fa9c84b4f1de6e1",
    "Repo": "https://github.com/uutils/coreutils"
  },
  {
    "Name": "pwd.exe",
    "Size": "820.74 kB",
    "ModTime": "2024-05-17T23:43:52.397663100Z",
    "Source": "https://bin.ajam.dev/x64_Windows/pwd.exe",
    "B3SUM": "a27f8b5f7a70580d73c14a6f8b3eab2c6eac5688cef9cbf48f0b638612df6819",
    "SHA256": "7a46e9e8a6052278c3f6e288d40b575bad5ad89015c8fbc0d9121b5be79c539f",
    "Repo": "https://github.com/uutils/coreutils"
  },
  {
    "Name": "quotes-escaper.exe",
    "Size": "1.56 MB",
    "ModTime": "2024-05-17T23:43:53.398099600Z",
    "Source": "https://bin.ajam.dev/x64_Windows/quotes-escaper.exe",
    "B3SUM": "54ecbba56028017202e7ec86907e1702fe96bf8d65be29b389ee980d642a4b4d",
    "SHA256": "87768a09fa9586ce14264a3e3e942aa11e19d683a5c63be325dd1dbcedfb8d3c",
    "Repo": "hhttps://github.com/Azathothas/Arsenal"
  },
  {
    "Name": "readlink.exe",
    "Size": "880.64 kB",
    "ModTime": "2024-05-17T23:43:54.398458600Z",
    "Source": "https://bin.ajam.dev/x64_Windows/readlink.exe",
    "B3SUM": "bbeab07ac04b6b098a9d7674d25b7b036bfbf01e544e827c7042ec8d43af3fa0",
    "SHA256": "f4612770ede9324ed1f1a8d8a2efc2ae3afd9e7c0d2e0237a20b299f72abc2f0",
    "Repo": "https://github.com/uutils/coreutils"
  },
  {
    "Name": "realpath.exe",
    "Size": "884.22 kB",
    "ModTime": "2024-05-17T23:43:55.399241700Z",
    "Source": "https://bin.ajam.dev/x64_Windows/realpath.exe",
    "B3SUM": "ae810c4aae5fe1cfa7f689835595ccccfa2e61ff124f1284700bb90b7ad754f9",
    "SHA256": "d26450a7d67b49657228bf0c08186b5ccaaa562c9fc6c73f6cc99f1deb599db8",
    "Repo": "https://github.com/uutils/coreutils"
  },
  {
    "Name": "rg.exe",
    "Size": "5.33 MB",
    "ModTime": "2024-05-17T23:43:56.461924100Z",
    "Source": "https://bin.ajam.dev/x64_Windows/rg.exe",
    "B3SUM": "8fbdd5429a69a838a3328a4fa4acab8fb6021306998dc8003b3777ac2ed07204",
    "SHA256": "9a8bdc1c2fd37e2042e22b18b7af26a0703454be207a3aca1025fc61a1ac2cca",
    "Repo": "https://github.com/BurntSushi/ripgrep"
  },
  {
    "Name": "rm.exe",
    "Size": "909.82 kB",
    "ModTime": "2024-05-17T23:43:57.399948700Z",
    "Source": "https://bin.ajam.dev/x64_Windows/rm.exe",
    "B3SUM": "63c43ca28461978d4b4c3702f2ccbad928087dc53076cf13a0ed0f998e5bd187",
    "SHA256": "821aa58f99c0794068e4c94e8a0e139c3ac537a7ff9d8aaa3f56b8aff81704ca",
    "Repo": "https://github.com/uutils/coreutils"
  },
  {
    "Name": "rmdir.exe",
    "Size": "835.07 kB",
    "ModTime": "2024-05-17T23:43:58.400344800Z",
    "Source": "https://bin.ajam.dev/x64_Windows/rmdir.exe",
    "B3SUM": "f7f5773514029c1d1f0d936b56fc3dca0be966e8944918664bdde27c0903339f",
    "SHA256": "22aadae40371c6de81a86ce4d315e15c960e03b0f00f426cf849dba8482a5680",
    "Repo": "https://github.com/uutils/coreutils"
  },
  {
    "Name": "scp.exe",
    "Size": "456.7 kB",
    "ModTime": "2024-05-17T23:43:59.385124100Z",
    "Source": "https://bin.ajam.dev/x64_Windows/scp.exe",
    "B3SUM": null,
    "SHA256": null,
    "Repo": null
  },
  {
    "Name": "seq.exe",
    "Size": "1.04 MB",
    "ModTime": "2024-05-17T23:44:00.416739100Z",
    "Source": "https://bin.ajam.dev/x64_Windows/seq.exe",
    "B3SUM": "1c015e8ab7aceef7bad0d2ea88132844c2864b14647a10bd1b266b431373b75a",
    "SHA256": "0ad7f69339a2204c706cb5bcf68d291a5c6d6cc78902541ecca3e134dbb1bf21",
    "Repo": "https://github.com/uutils/coreutils"
  },
  {
    "Name": "sftp-server.exe",
    "Size": "374.27 kB",
    "ModTime": "2024-05-17T23:44:01.417077400Z",
    "Source": "https://bin.ajam.dev/x64_Windows/sftp-server.exe",
    "B3SUM": null,
    "SHA256": null,
    "Repo": null
  },
  {
    "Name": "shell2http.exe",
    "Size": "5.67 MB",
    "ModTime": "2024-05-17T23:44:02.511339300Z",
    "Source": "https://bin.ajam.dev/x64_Windows/shell2http.exe",
    "B3SUM": "3e511206edf15b0cfe6715e10a91e63c59e68af17b5e654f0521884f4560957b",
    "SHA256": "3e69a5f8c0f5b8dc2a8352183a84b414fc72728c454f223786c431b656664ebc",
    "Repo": "https://github.com/msoap/shell2http"
  },
  {
    "Name": "shred.exe",
    "Size": "897.54 kB",
    "ModTime": "2024-05-17T23:44:03.450067300Z",
    "Source": "https://bin.ajam.dev/x64_Windows/shred.exe",
    "B3SUM": "31b1702abbbae28e89a2bb168f50e8d49271eb1ddf9b450092a73a07a7a699ad",
    "SHA256": "099a53fac1244a573d2da25b598ed9dbbc36785a6d7e5fa8f2ca5b0166c3cf76",
    "Repo": "https://github.com/uutils/coreutils"
  },
  {
    "Name": "shuf.exe",
    "Size": "911.36 kB",
    "ModTime": "2024-05-17T23:44:04.450425200Z",
    "Source": "https://bin.ajam.dev/x64_Windows/shuf.exe",
    "B3SUM": "695e1098e04406cac2a42117323abec198a0fafab35787e7a07aa61a5fcfc2b8",
    "SHA256": "f1fc0794327a96dc5dba53a2400cc4ff64e04354e66b16b7c56f52f107f0dc86",
    "Repo": "https://github.com/uutils/coreutils"
  },
  {
    "Name": "sing-box.exe",
    "Size": "30.45 MB",
    "ModTime": "2024-05-17T23:44:05.844898600Z",
    "Source": "https://bin.ajam.dev/x64_Windows/sing-box.exe",
    "B3SUM": "d42f474be1120694bbac63f15de1c90c01e43718e2c4d53cf4be39c988d68820",
    "SHA256": "713f81a1184a6e116bd62e9aaaf1e0454e9cfbabdb2da8f750ebb270d3552e77",
    "Repo": "https://github.com/SagerNet/sing-box"
  },
  {
    "Name": "sish.exe",
    "Size": "20.42 MB",
    "ModTime": "2024-05-17T23:44:06.704797100Z",
    "Source": "https://bin.ajam.dev/x64_Windows/sish.exe",
    "B3SUM": "1f17792db5f4901e94d1506de0f61a6953483581d4b6fc381caf8dab52de9587",
    "SHA256": "e1b49502eaaa29426e2a49a6281efca2673ea6c2fb96de3c0f86b37a2a1dd0c5",
    "Repo": "https://github.com/antoniomika/sish"
  },
  {
    "Name": "sleep.exe",
    "Size": "839.17 kB",
    "ModTime": "2024-05-17T23:44:07.455298200Z",
    "Source": "https://bin.ajam.dev/x64_Windows/sleep.exe",
    "B3SUM": "184fa44a97320988927576b570a2ea09bf91bea384aefd8cc4901b53947d07cc",
    "SHA256": "67aac72001e62c81d369ec99518feef01a08b32decc21073e9c0a8830d264e85",
    "Repo": "https://github.com/uutils/coreutils"
  },
  {
    "Name": "smartdns-rs.exe",
    "Size": "9.36 MB",
    "ModTime": "2024-05-17T23:44:08.565009800Z",
    "Source": "https://bin.ajam.dev/x64_Windows/smartdns-rs.exe",
    "B3SUM": "a0982d93cf138a313100cb25fb4f5d1fa7c699c0dc5c32277dc985a4b393daf0",
    "SHA256": "cf6e5015ae2a281f8929d9d90405c08407690013191b640ed25666a75750eb93",
    "Repo": "https://github.com/mokeyish/smartdns-rs"
  },
  {
    "Name": "smartdns.exe",
    "Size": "9.36 MB",
    "ModTime": "2024-05-11T18:00:17.222845600Z",
    "Source": "https://bin.ajam.dev/x64_Windows/smartdns.exe",
    "B3SUM": null,
    "SHA256": null,
    "Repo": null
  },
  {
    "Name": "sort.exe",
    "Size": "1.67 MB",
    "ModTime": "2024-05-17T23:44:09.471417200Z",
    "Source": "https://bin.ajam.dev/x64_Windows/sort.exe",
    "B3SUM": "f9131e158e4d5fb852ff8139aa396d7abb86bc491350caab802795753f046e40",
    "SHA256": "46e8d07385ca751bd9d502a72db6d35ec21e11863b3746996e69c84a0354e724",
    "Repo": "https://github.com/uutils/coreutils"
  },
  {
    "Name": "split.exe",
    "Size": "966.14 kB",
    "ModTime": "2024-05-17T23:44:10.457072900Z",
    "Source": "https://bin.ajam.dev/x64_Windows/split.exe",
    "B3SUM": "5bc66046168410f90ea48a9828c2efdbf1e58d50e46be682f7bd0de96eee0449",
    "SHA256": "edf81a4767ed06fb46dfb75a10462528697f25ba2ee7424f8414b550d0ffde6c",
    "Repo": "https://github.com/uutils/coreutils"
  },
  {
    "Name": "ssh-add.exe",
    "Size": "604.67 kB",
    "ModTime": "2024-05-17T23:44:11.457460000Z",
    "Source": "https://bin.ajam.dev/x64_Windows/ssh-add.exe",
    "B3SUM": null,
    "SHA256": null,
    "Repo": null
  },
  {
    "Name": "ssh-agent.exe",
    "Size": "556.03 kB",
    "ModTime": "2024-05-17T23:44:12.458151200Z",
    "Source": "https://bin.ajam.dev/x64_Windows/ssh-agent.exe",
    "B3SUM": null,
    "SHA256": null,
    "Repo": null
  },
  {
    "Name": "ssh-keygen.exe",
    "Size": "854.53 kB",
    "ModTime": "2024-05-17T23:44:13.458572500Z",
    "Source": "https://bin.ajam.dev/x64_Windows/ssh-keygen.exe",
    "B3SUM": null,
    "SHA256": null,
    "Repo": null
  },
  {
    "Name": "ssh-keyscan.exe",
    "Size": "665.09 kB",
    "ModTime": "2024-05-17T23:44:14.458933300Z",
    "Source": "https://bin.ajam.dev/x64_Windows/ssh-keyscan.exe",
    "B3SUM": null,
    "SHA256": null,
    "Repo": null
  },
  {
    "Name": "ssh-pkcs11-helper.exe",
    "Size": "519.68 kB",
    "ModTime": "2024-05-17T23:44:15.443862300Z",
    "Source": "https://bin.ajam.dev/x64_Windows/ssh-pkcs11-helper.exe",
    "B3SUM": null,
    "SHA256": null,
    "Repo": null
  },
  {
    "Name": "ssh-shellhost.exe",
    "Size": "179.2 kB",
    "ModTime": "2024-05-17T23:44:16.444344400Z",
    "Source": "https://bin.ajam.dev/x64_Windows/ssh-shellhost.exe",
    "B3SUM": null,
    "SHA256": null,
    "Repo": null
  },
  {
    "Name": "ssh-sk-helper.exe",
    "Size": "659.46 kB",
    "ModTime": "2024-05-17T23:44:17.460732300Z",
    "Source": "https://bin.ajam.dev/x64_Windows/ssh-sk-helper.exe",
    "B3SUM": null,
    "SHA256": null,
    "Repo": null
  },
  {
    "Name": "ssh.exe",
    "Size": "1.24 MB",
    "ModTime": "2024-05-17T23:44:18.461124600Z",
    "Source": "https://bin.ajam.dev/x64_Windows/ssh.exe",
    "B3SUM": null,
    "SHA256": null,
    "Repo": null
  },
  {
    "Name": "sshd.exe",
    "Size": "1.33 MB",
    "ModTime": "2024-05-17T23:44:19.461453400Z",
    "Source": "https://bin.ajam.dev/x64_Windows/sshd.exe",
    "B3SUM": null,
    "SHA256": null,
    "Repo": null
  },
  {
    "Name": "stP1kAlM",
    "Size": "0 B",
    "ModTime": "2024-03-30T12:20:45.532136400Z",
    "Source": "https://bin.ajam.dev/x64_Windows/stP1kAlM",
    "B3SUM": null,
    "SHA256": null,
    "Repo": null
  },
  {
    "Name": "step.exe",
    "Size": "37.12 MB",
    "ModTime": "2024-05-17T23:44:20.947239400Z",
    "Source": "https://bin.ajam.dev/x64_Windows/step.exe",
    "B3SUM": "6b76a673799d1c239b7199106393bfd4e1fb88d49376582500d33ad6c9f84c51",
    "SHA256": "803d6186c5518f8113e1b726ddc608c9fd0da24d39083429b9b3503db0b40a8c",
    "Repo": "https://github.com/smallstep/cli"
  },
  {
    "Name": "stiG2Kb7",
    "Size": "0 B",
    "ModTime": "2024-03-30T12:20:46.532861400Z",
    "Source": "https://bin.ajam.dev/x64_Windows/stiG2Kb7",
    "B3SUM": null,
    "SHA256": null,
    "Repo": null
  },
  {
    "Name": "stunner.exe",
    "Size": "7.46 MB",
    "ModTime": "2024-05-17T23:44:21.540991900Z",
    "Source": "https://bin.ajam.dev/x64_Windows/stunner.exe",
    "B3SUM": "7fdba2c7803c7ee7f6b4cfe4fcea7fbb96b1a9dfe909bc71f7c1fbd07f033b53",
    "SHA256": "6e0efd4f3014b435403a5e45bc722b5735d98a3252c8d8c35003a3a806dc15cd",
    "Repo": "https://github.com/firefart/stunner"
  },
  {
    "Name": "sum.exe",
    "Size": "849.41 kB",
    "ModTime": "2024-05-17T23:44:22.463686500Z",
    "Source": "https://bin.ajam.dev/x64_Windows/sum.exe",
    "B3SUM": "05c56e37735ab79731a5589d41f46d5f6bd9e01db6844426845cc8e4c97e1839",
    "SHA256": "e5688bbbb077e7a7e6506c963d2c1aab9c77124ed3bd40325a1412a1aa2780fd",
    "Repo": "https://github.com/uutils/coreutils"
  },
  {
    "Name": "sync.exe",
    "Size": "835.58 kB",
    "ModTime": "2024-05-17T23:44:23.464102900Z",
    "Source": "https://bin.ajam.dev/x64_Windows/sync.exe",
    "B3SUM": "840d646333552811eb76acac86d541bda2fa58bef8d3b1eb869146fd761d2131",
    "SHA256": "3c4f527efe29265a77799bdefec0e2100a5a332138c9c28737916ee9b6ce3d83",
    "Repo": "https://github.com/uutils/coreutils"
  },
  {
    "Name": "tac.exe",
    "Size": "2.25 MB",
    "ModTime": "2024-05-17T23:44:24.480112400Z",
    "Source": "https://bin.ajam.dev/x64_Windows/tac.exe",
    "B3SUM": "cd6f805a395f4da256b8b3154703171c8ac8ff18e727e15fb5976f6a4274fddd",
    "SHA256": "7163458b3f37f284f4f1a384aab09cf6b6c68494d233ac0569175b5d17a000d4",
    "Repo": "https://github.com/uutils/coreutils"
  },
  {
    "Name": "tail.exe",
    "Size": "1.33 MB",
    "ModTime": "2024-05-17T23:44:25.465509800Z",
    "Source": "https://bin.ajam.dev/x64_Windows/tail.exe",
    "B3SUM": "a463b977d71d30889759b3dfbe2ff1683a51994cca9193b46f96a54fbaabcccc",
    "SHA256": "65731efeef57292c1e4d344e39d87155ac80b11b1ab1097ac39cf885c3b34754",
    "Repo": "https://github.com/uutils/coreutils"
  },
  {
    "Name": "tee.exe",
    "Size": "874.5 kB",
    "ModTime": "2024-05-17T23:44:26.465770200Z",
    "Source": "https://bin.ajam.dev/x64_Windows/tee.exe",
    "B3SUM": "4517987e756aab4be468aa172d5e3b86b61fa2ab26ce5327cd729b497b584316",
    "SHA256": "b858cb23e10ee75b59182ea79b7ac6bd0ae9633aa180fb92c775ef3b2176c28a",
    "Repo": "https://github.com/uutils/coreutils"
  },
  {
    "Name": "test.exe",
    "Size": "846.34 kB",
    "ModTime": "2024-05-17T23:44:27.466235000Z",
    "Source": "https://bin.ajam.dev/x64_Windows/test.exe",
    "B3SUM": "2f6d8ea12b18e7bb16d10f5c8ba506bd297e2de0ff29596eb4c6956dceb3312c",
    "SHA256": "97296ec6a29f274ddc70b49a4ea15f9c12813a68cdacbe33e1d04a25ebe11b88",
    "Repo": "https://github.com/uutils/coreutils"
  },
  {
    "Name": "touch.exe",
    "Size": "2.36 MB",
    "ModTime": "2024-05-17T23:44:28.482199700Z",
    "Source": "https://bin.ajam.dev/x64_Windows/touch.exe",
    "B3SUM": "8a9a15efc2638a42ffc75401dc49b06bacf1377caab150484ccbece6bfd0439b",
    "SHA256": "09f8b1bb29a9277f6c3154b5635ec4358ae40b389e52d84a5e6458d5069bc07f",
    "Repo": "https://github.com/uutils/coreutils"
  },
  {
    "Name": "tr.exe",
    "Size": "902.14 kB",
    "ModTime": "2024-05-17T23:44:29.467358000Z",
    "Source": "https://bin.ajam.dev/x64_Windows/tr.exe",
    "B3SUM": "db8257e30cea1b8ccd279f190f6c29b20c133307dbaf91bb7d99d5daac3fb59d",
    "SHA256": "d45a5af9874f6cfe84c6a105f333ed56d5fb0c48431d8b04b2775f064e759786",
    "Repo": "https://github.com/uutils/coreutils"
  },
  {
    "Name": "true.exe",
    "Size": "758.78 kB",
    "ModTime": "2024-05-17T23:44:30.457362000Z",
    "Source": "https://bin.ajam.dev/x64_Windows/true.exe",
    "B3SUM": "518c2272bdfea2f9e4368b9aab4f310f660e3a276cc0c2ed7b66b34264150122",
    "SHA256": "1b366e0d321a78d9c84a57a745637f58a98a99ccb7287cc28ff8a8d284397683",
    "Repo": "https://github.com/uutils/coreutils"
  },
  {
    "Name": "truncate.exe",
    "Size": "844.29 kB",
    "ModTime": "2024-05-17T23:44:31.473594900Z",
    "Source": "https://bin.ajam.dev/x64_Windows/truncate.exe",
    "B3SUM": "9d7e82c3e7a28615ececd8335c1d4dcbdf33dfa350e541c81c92a7b628bfaf71",
    "SHA256": "3e8ae4f6cc6633febc3bb00480cb18285f02c7a3684f753f2dc8c93cd9c6a5cb",
    "Repo": "https://github.com/uutils/coreutils"
  },
  {
    "Name": "trurl.exe",
    "Size": "7.04 MB",
    "ModTime": "2024-05-17T23:44:32.554434800Z",
    "Source": "https://bin.ajam.dev/x64_Windows/trurl.exe",
    "B3SUM": "a905829cd293f77c0f3e5bebd326f0569eb8cf0371b812234f13fa734bb0ba49",
    "SHA256": "05bed28dc57fe6fa2c09db8ef1e2c7494040787d08b8176a47ce6137b3cc0f3c",
    "Repo": "https://github.com/stunnel/static-curl"
  },
  {
    "Name": "tsort.exe",
    "Size": "879.1 kB",
    "ModTime": "2024-05-17T23:44:33.476745700Z",
    "Source": "https://bin.ajam.dev/x64_Windows/tsort.exe",
    "B3SUM": "ed12f614bbbbcb3fccf0414559190f9ecbfd5190346c17907be845a2efbf76ec",
    "SHA256": "83547b9fc8749cf2165653433bbe096d28c4c6309db4fc9b20f374e3b98e7f38",
    "Repo": "https://github.com/uutils/coreutils"
  },
  {
    "Name": "tssh.exe",
    "Size": "10.84 MB",
    "ModTime": "2024-05-17T23:44:34.601930300Z",
    "Source": "https://bin.ajam.dev/x64_Windows/tssh.exe",
    "B3SUM": "90c220a1a1f6f8967253222815166bd5642eed3ec207c209a9b0d8c8d77e9d1e",
    "SHA256": "edf4a83e70d54d97d8819b014bb04376e40daa97333c71d8575e0ae852263403",
    "Repo": "https://github.com/trzsz/trzsz-ssh"
  },
  {
    "Name": "uname.exe",
    "Size": "847.36 kB",
    "ModTime": "2024-05-17T23:44:35.478150700Z",
    "Source": "https://bin.ajam.dev/x64_Windows/uname.exe",
    "B3SUM": "6e67f31a59875df98b68b5194e6246ea48eda911f6c0233d939262a60901e6dc",
    "SHA256": "716225b159ddead3cf91446031c3f6ca0d3877bd7a3101a9674999a6b69bd1d6",
    "Repo": "https://github.com/uutils/coreutils"
  },
  {
    "Name": "unexpand.exe",
    "Size": "870.91 kB",
    "ModTime": "2024-05-17T23:44:36.478272400Z",
    "Source": "https://bin.ajam.dev/x64_Windows/unexpand.exe",
    "B3SUM": "1aa260fc73f20ecdf37ddf603af75ca31b3dc73b9f9e0e0827233414e9535219",
    "SHA256": "0306ad822fd61545f59e171d5b856044f0154c17c27521c40621b79703dc3701",
    "Repo": "https://github.com/uutils/coreutils"
  },
  {
    "Name": "uniq.exe",
    "Size": "906.75 kB",
    "ModTime": "2024-05-17T23:44:37.478734800Z",
    "Source": "https://bin.ajam.dev/x64_Windows/uniq.exe",
    "B3SUM": "022f66fd2c4b04d07430c2b31c837b847bed9d0ecad8476a12570b6b68c65a1a",
    "SHA256": "d89343a282d87dd76467a942d1d5ef50cfed6e95ce1b7f7a298f3ac93a3ddf94",
    "Repo": "https://github.com/uutils/coreutils"
  },
  {
    "Name": "unlink.exe",
    "Size": "828.42 kB",
    "ModTime": "2024-05-17T23:44:38.479038100Z",
    "Source": "https://bin.ajam.dev/x64_Windows/unlink.exe",
    "B3SUM": "e7ea66753a38eb22e32ea3772fb77f7c69d02ec2a9b4adcac7bba01bf575bba2",
    "SHA256": "47b3e91d8ef38cf2fcf8e10870fe677702c6ff1c7f89dd3adb881444c408a11a",
    "Repo": "https://github.com/uutils/coreutils"
  },
  {
    "Name": "upx.exe",
    "Size": "564.22 kB",
    "ModTime": "2024-03-29T11:24:05.355607900Z",
    "Source": "https://bin.ajam.dev/x64_Windows/upx.exe",
    "B3SUM": null,
    "SHA256": null,
    "Repo": null
  },
  {
    "Name": "vdir.exe",
    "Size": "1.25 MB",
    "ModTime": "2024-05-17T23:44:39.479398000Z",
    "Source": "https://bin.ajam.dev/x64_Windows/vdir.exe",
    "B3SUM": "12fa4d35b1630bfd220a2e95d51c44ccf910e2548cc2f142c32d215bf23217ed",
    "SHA256": "a4b90bfc1baa731531124f539ec29b959c13fd67440c2173e2688f849e5eec61",
    "Repo": "https://github.com/uutils/coreutils"
  },
  {
    "Name": "wc.exe",
    "Size": "922.62 kB",
    "ModTime": "2024-05-17T23:44:40.495212900Z",
    "Source": "https://bin.ajam.dev/x64_Windows/wc.exe",
    "B3SUM": "be0fda103e37b5cf9905e0e5ec602958e5deebc58ee96193a43bdb59c4b296ef",
    "SHA256": "0a14a0b43086e3fb5a5d03738bb972d7d6bd809f177123123edf291b65fb1c49",
    "Repo": "https://github.com/uutils/coreutils"
  },
  {
    "Name": "wget2.exe",
    "Size": "4.61 MB",
    "ModTime": "2024-05-17T23:44:41.542533900Z",
    "Source": "https://bin.ajam.dev/x64_Windows/wget2.exe",
    "B3SUM": "8f8970761328e8a24ad818933e19f91a825e86a20227777bcc7205af18e1a085",
    "SHA256": "b1bb5e9163d5b6d31d33e6d5ac01a5e8eeded07ab1a7a332d93f945b81841e50",
    "Repo": "https://github.com/rockdaboot/wget2"
  },
  {
    "Name": "whoami.exe",
    "Size": "810.5 kB",
    "ModTime": "2024-05-17T23:44:42.496021400Z",
    "Source": "https://bin.ajam.dev/x64_Windows/whoami.exe",
    "B3SUM": "400631a917f652f3d8b019848f314e9cf918088b8ff3263816aa56053b86ce91",
    "SHA256": "9ef89b8cfa37e992bc690cbd21dcd43885bf53f4dd2738a20e78b5c54be8d7f5",
    "Repo": "https://github.com/uutils/coreutils"
  },
  {
    "Name": "wldd.exe",
    "Size": "1.24 MB",
    "ModTime": "2024-05-17T23:44:43.496342600Z",
    "Source": "https://bin.ajam.dev/x64_Windows/wldd.exe",
    "B3SUM": "43ed1bb8170ba6b35f043d21525fd5c766a4d56c62d36d8e5c6da92b07c1f35f",
    "SHA256": "6e8bd822ecf09752c8c8f0806935d706ed753b7330e47751a99fdb5cf8ae1bc9",
    "Repo": "https://github.com/marcoesposito1988/dependency_runner"
  },
  {
    "Name": "xargs-rs.exe",
    "Size": "884.22 kB",
    "ModTime": "2024-05-17T23:44:44.496546600Z",
    "Source": "https://bin.ajam.dev/x64_Windows/xargs-rs.exe",
    "B3SUM": "917578a3f9006cfa3e32edd607e4dc998166f397a513370a532951e34ed84ec1",
    "SHA256": "007ebd585bc034b65bd12bb9fa2fdb2432f54c92b780475b6ea21529e2690881",
    "Repo": "https://github.com/uutils/findutils"
  },
  {
    "Name": "xargs.exe",
    "Size": "884.22 kB",
    "ModTime": "2024-05-17T23:44:45.497126900Z",
    "Source": "https://bin.ajam.dev/x64_Windows/xargs.exe",
    "B3SUM": "0f6e2a61dc049325e6954759c2054e78810c39606aabb5bb8e5d8f237dadbde2",
    "SHA256": "62e9ff212136fdb9f2768d97a1bb2e176abd9450ee5f6e72d7846fba63c5bd2b",
    "Repo": "https://github.com/uutils/findutils"
  },
  {
    "Name": "yes.exe",
    "Size": "807.42 kB",
    "ModTime": "2024-05-17T23:44:46.497297100Z",
    "Source": "https://bin.ajam.dev/x64_Windows/yes.exe",
    "B3SUM": "26ad3bf51520820d22b552358c5be59ee176e7a7f737c4763b2b7a4f7cea0d4e",
    "SHA256": "f56b1e249734003329e5da445418aa31904b976b2b60ab1663416b028c694005",
    "Repo": "https://github.com/uutils/coreutils"
  },
  {
    "Name": "yq.exe",
    "Size": "10.35 MB",
    "ModTime": "2024-03-29T11:24:05.312053200Z",
    "Source": "https://bin.ajam.dev/x64_Windows/yq.exe",
    "B3SUM": null,
    "SHA256": null,
    "Repo": null
  },
  {
    "Name": "yt-dlp.exe",
    "Size": "173.06 kB",
    "ModTime": "2024-05-17T23:44:47.492023200Z",
    "Source": "https://bin.ajam.dev/x64_Windows/yt-dlp.exe",
    "B3SUM": "82851436ef53bb07b9e4a42b1d19db8be25d46c11c963acda3371eee3f358996",
    "SHA256": "44597a609b4e758a882823462f425cdc32bafe7603b2849e5592a8fc00aa73d0",
    "Repo": "https://github.com/yt-dlp/yt-dlp"
  }
]
