[
  {
    "name": "act",
    "description": "Run your GitHub Actions locally",
    "download_url": "https://bin.ajam.dev/arm64_v8a_Android/act",
    "size": "17.42 MB",
    "b3sum": "fd31413c009f24aeeda5643d88960da7582a885edb929584baf4eefbd568314a",
    "sha256": "ce6f034d18527dff9ce0f0bd41decf64d58f56eeef5829d4019415ca57a46343",
    "build_date": "2024-06-16T22:41:18",
    "repo_url": "https://github.com/nektos/act",
    "repo_author": "nektos",
    "repo_info": "Run your GitHub Actions locally 🚀",
    "repo_updated": "2024-06-17T12:25:31Z",
    "repo_released": "2024-06-01T02:21:41Z",
    "repo_version": "v0.2.63",
    "repo_stars": "51568",
    "repo_language": "Go",
    "repo_license": "MIT License",
    "repo_topics": "ci, devops, github-actions, golang",
    "web_url": "https://github.com/nektos/act",
    "extra_bins": ""
  },
  {
    "name": "actionlint",
    "description": "Static checker for GitHub Actions workflow files",
    "download_url": "https://bin.ajam.dev/arm64_v8a_Android/actionlint",
    "size": "5.37 MB",
    "b3sum": "cbab1cc80aaa8066aabb9d01534dc1d34cba475e6cb3679d520b8f98fbcb6d8e",
    "sha256": "0a8c17b2b3208f327d5b0cd9c94910312f223f58905eba8a664f89bc28c493cd",
    "build_date": "2024-06-09T22:39:32",
    "repo_url": "https://github.com/rhysd/actionlint",
    "repo_author": "rhysd",
    "repo_info": ":octocat: Static checker for GitHub Actions workflow files",
    "repo_updated": "2024-06-11T15:56:34Z",
    "repo_released": "2024-05-28T11:50:24Z",
    "repo_version": "v1.7.1",
    "repo_stars": "2531",
    "repo_language": "Go",
    "repo_license": "MIT License",
    "repo_topics": "actions, ci, github-actions, lint, linter",
    "web_url": "https://github.com/rhysd/actionlint",
    "extra_bins": ""
  },
  {
    "name": "adig",
    "description": "A command-line tool that allows you to perform DNS lookups from the command line",
    "download_url": "https://bin.ajam.dev/arm64_v8a_Android/adig",
    "size": "168.81 kB",
    "b3sum": "b82b4b61b00d533954c42268320ff2b536112c47dfcfaa9fd0ae7c3b8ff893d4",
    "sha256": "fb44a9fdb761f7fb0b91d4cd2a3239c2a4f8b33a6255bb9c772cad2b7aacd9c0",
    "build_date": "2024-06-16T22:42:41",
    "repo_url": "https://github.com/c-ares/c-ares",
    "repo_author": "c-ares",
    "repo_info": "A C library for asynchronous DNS requests",
    "repo_updated": "2024-06-17T20:40:08Z",
    "repo_released": "2024-06-07T10:54:58Z",
    "repo_version": "v1.30.0",
    "repo_stars": "1796",
    "repo_language": "C",
    "repo_license": "Other",
    "repo_topics": "async, c, dns, dns-queries, library, resolver",
    "web_url": "https://github.com/c-ares/c-ares",
    "extra_bins": ""
  },
  {
    "name": "anew-rs",
    "description": "A fast, simple, recursive content discovery tool written in Rust.",
    "download_url": "https://bin.ajam.dev/arm64_v8a_Android/anew-rs",
    "size": "943.82 kB",
    "b3sum": "0025e63f6fd76d566440e0814be7ed33928a2719151182064e146015dcd6fae4",
    "sha256": "c626c0eb9b35a9d4afff78cddb63c53445f441d97c18efd3d45294bab8686f05",
    "build_date": "2024-06-14T22:42:39",
    "repo_url": "https://github.com/zer0yu/anew",
    "repo_author": "zer0yu",
    "repo_info": "A tool for adding new lines to files, skipping duplicates and written in Rust!",
    "repo_updated": "2024-05-08T12:29:15Z",
    "repo_released": "2023-11-23T16:11:10Z",
    "repo_version": "v0.1.0",
    "repo_stars": "11",
    "repo_language": "Rust",
    "repo_license": "MIT License",
    "repo_topics": "",
    "web_url": "https://github.com/zer0yu/anew",
    "extra_bins": ""
  },
  {
    "name": "aria2c",
    "description": "Download with resuming and segmented downloading",
    "download_url": "https://bin.ajam.dev/arm64_v8a_Android/aria2c",
    "size": "9.3 MB",
    "b3sum": "bc1acd39ad1cdae27671fb0ea9f8b967a1f99ec6b30242517100ba4aecfafeb6",
    "sha256": "f05fb3fd985a3c13ce09300c7ac2cbe9d17179f75c38de4aaacd257b90ba5516",
    "build_date": "2024-06-16T22:51:39",
    "repo_url": "https://github.com/aria2/aria2",
    "repo_author": "aria2",
    "repo_info": "aria2 is a lightweight multi-protocol & multi-source, cross platform download utility operated in command-line. It supports HTTP/HTTPS, FTP, SFTP, BitTorrent and Metalink.",
    "repo_updated": "2024-06-16T01:19:59Z",
    "repo_released": "2023-11-15T12:07:32Z",
    "repo_version": "release-1.37.0",
    "repo_stars": "33994",
    "repo_language": "C++",
    "repo_license": "GNU General Public License v2.0",
    "repo_topics": "bittorrent, cpp11, download, ftp, http, metalink, rpc, sftp",
    "web_url": "https://github.com/aria2/aria2",
    "extra_bins": ""
  },
  {
    "name": "axel",
    "description": "A lightweight download accelerator",
    "download_url": "https://bin.ajam.dev/arm64_v8a_Android/axel",
    "size": "3.76 MB",
    "b3sum": "1dd5c4f0b091d5b8419710f1c0b824f6ece517f8ff852d01e3b8ffc5c2b68c9e",
    "sha256": "3c341d178cef8723ebe7b46c5a61c33bb77ab15b33acba2a3647e2dddb36df9b",
    "build_date": "2024-06-16T22:55:46",
    "repo_url": "https://github.com/axel/axel",
    "repo_author": "",
    "repo_info": "",
    "repo_updated": "",
    "repo_released": "",
    "repo_version": "",
    "repo_stars": "",
    "repo_language": "",
    "repo_license": "",
    "repo_topics": "",
    "web_url": "https://github.com/axel/axel",
    "extra_bins": ""
  },
  {
    "name": "bash",
    "description": "GNU Bourne-Again Shell, the de facto standard shell on Linux",
    "download_url": "https://bin.ajam.dev/arm64_v8a_Android/bash",
    "size": "1.78 MB",
    "b3sum": "76f1f05cbe10be06911e4c3c120564ce6d96015886e0efd91fc9464881d8aad5",
    "sha256": "c7a1ff7b863322709d752a7345ae8caeef9a94644edcf2c8c36e3a45b799f682",
    "build_date": "2024-06-16T22:57:49",
    "repo_url": "",
    "web_url": "https://www.bash.ws/",
    "extra_bins": ""
  },
  {
    "name": "bigdl",
    "description": "📦 Poor mans package manager.",
    "download_url": "https://bin.ajam.dev/arm64_v8a_Android/bigdl",
    "size": "6.69 MB",
    "b3sum": "9a594a03b87b501109eaba07b489df3cfd33eb9538f18313aef9627a43414987",
    "sha256": "7183004c071964b2755ef3ddfc7c88f05e199746d3920551bffab8be39c6f45b",
    "build_date": "2024-06-16T23:00:36",
    "repo_url": "https://github.com/xplshn/bigdl",
    "repo_author": "xplshn",
    "repo_info": "📦 Poor mans package manager. +1440 statically linked binaries in the repos!",
    "repo_updated": "2024-06-16T04:57:26Z",
    "repo_released": "2024-06-13T15:51:43Z",
    "repo_version": "1.6.8",
    "repo_stars": "7",
    "repo_language": "Go",
    "repo_license": "Other",
    "repo_topics": "binary-manager, cli, dependency-checker, fast, go, golang, package-manager, runner, static, static-binaries, static-binary",
    "web_url": "https://github.com/xplshn/bigdl",
    "extra_bins": ""
  },
  {
    "name": "curl",
    "description": "A command line tool for transferring files with URL syntax",
    "download_url": "https://bin.ajam.dev/arm64_v8a_Android/curl",
    "size": "5.31 MB",
    "b3sum": "7883761a1dc93c4153a22393eb09d586968b8780d2d019a6dc8e01a11fd8c1b4",
    "sha256": "97c655deec780f9abbcdf97dae3520ad4ffd48a5d8fc2c702c73372a5d446bcd",
    "build_date": "2024-06-16T23:03:20",
    "repo_url": "https://github.com/curl/curl",
    "repo_author": "curl",
    "repo_info": "A command line tool and library for transferring data with URL syntax, supporting DICT, FILE, FTP, FTPS, GOPHER, GOPHERS, HTTP, HTTPS, IMAP, IMAPS, LDAP, LDAPS, MQTT, POP3, POP3S, RTMP, RTMPS, RTSP, SCP, SFTP, SMB, SMBS, SMTP, SMTPS, TELNET, TFTP, WS and WSS. libcurl offers a myriad of powerful features",
    "repo_updated": "2024-06-17T21:10:13Z",
    "repo_released": "2024-05-22T06:02:33Z",
    "repo_version": "curl-8_8_0",
    "repo_stars": "34652",
    "repo_language": "C",
    "repo_license": "Other",
    "repo_topics": "c, client, curl, ftp, gopher, hacktoberfest, http, https, imaps, ldap, libcurl, library, mqtt, pop3, scp, sftp, transfer-data, transferring-data, user-agent, websocket",
    "web_url": "https://github.com/curl/curl",
    "extra_bins": "curl_cacert.pem"
  },
  {
    "name": "curl_cacert.pem",
    "description": "A command line tool for transferring files with URL syntax",
    "download_url": "https://bin.ajam.dev/arm64_v8a_Android/curl_cacert.pem",
    "size": "229.65 kB",
    "b3sum": "b58055305c0fb5874b11a4e49ba49356674d8ce927aaea6ffa2632d7f4a53653",
    "sha256": "1794c1d4f7055b7d02c2170337b61b48a2ef6c90d77e95444fd2596f4cac609f",
    "build_date": "2024-05-07T08:03:10",
    "repo_url": "https://github.com/curl/curl",
    "repo_author": "curl",
    "repo_info": "A command line tool and library for transferring data with URL syntax, supporting DICT, FILE, FTP, FTPS, GOPHER, GOPHERS, HTTP, HTTPS, IMAP, IMAPS, LDAP, LDAPS, MQTT, POP3, POP3S, RTMP, RTMPS, RTSP, SCP, SFTP, SMB, SMBS, SMTP, SMTPS, TELNET, TFTP, WS and WSS. libcurl offers a myriad of powerful features",
    "repo_updated": "2024-06-17T21:10:13Z",
    "repo_released": "2024-05-22T06:02:33Z",
    "repo_version": "curl-8_8_0",
    "repo_stars": "34652",
    "repo_language": "C",
    "repo_license": "Other",
    "repo_topics": "c, client, curl, ftp, gopher, hacktoberfest, http, https, imaps, ldap, libcurl, library, mqtt, pop3, scp, sftp, transfer-data, transferring-data, user-agent, websocket",
    "web_url": "https://github.com/curl/curl",
    "extra_bins": "curl"
  },
  {
    "name": "jless",
    "description": "command-line JSON viewer designed for reading, exploring, and searching through JSON data.",
    "download_url": "https://bin.ajam.dev/arm64_v8a_Android/jless",
    "size": "2.02 MB",
    "b3sum": "90d9e869047e75d2b8be16ffd3e0bcf8942704be311cbcf5c963d2573a66270d",
    "sha256": "23718272c685d8f0d085e22aaefb39acae91d95936011e8c8512443c9d140796",
    "build_date": "2024-06-02T23:01:25",
    "repo_url": "https://github.com/PaulJuliusMartinez/jless",
    "repo_author": "PaulJuliusMartinez",
    "repo_info": "jless is a command-line JSON viewer designed for reading, exploring, and searching through JSON data.",
    "repo_updated": "2024-06-01T20:34:10Z",
    "repo_released": "2023-07-17T02:51:34Z",
    "repo_version": "v0.9.0",
    "repo_stars": "4577",
    "repo_language": "Rust",
    "repo_license": "MIT License",
    "repo_topics": "cli, json, rust",
    "web_url": "https://github.com/PaulJuliusMartinez/jless",
    "extra_bins": ""
  },
  {
    "name": "pingmole",
    "description": "CLI that helps to filter pingmole servers and pick the closest one.",
    "download_url": "https://bin.ajam.dev/arm64_v8a_Android/pingmole",
    "size": "6.93 MB",
    "b3sum": "5096b711a10d5ed757da956ea480430cfd37a473947145ae4ebb940f565f7edf",
    "sha256": "5669d704e730ece91f3fdfb4d8cf8d06604e75121f39c3c52dd5522ae33384dd",
    "build_date": "2024-06-16T23:08:07",
    "repo_url": "https://github.com/norskeld/pingmole",
    "repo_author": "norskeld",
    "repo_info": "CLI that helps to filter Mullvad servers and pick the closest one.",
    "repo_updated": "2024-04-16T11:28:34Z",
    "repo_released": "",
    "repo_version": "",
    "repo_stars": "4",
    "repo_language": "Rust",
    "repo_license": "MIT License",
    "repo_topics": "cli, mullvad, rust",
    "web_url": "https://github.com/norskeld/pingmole",
    "extra_bins": ""
  },
  {
    "name": "pspy",
    "description": "Monitor linux processes without root permissions",
    "download_url": "https://bin.ajam.dev/arm64_v8a_Android/pspy",
    "size": "3.76 MB",
    "b3sum": "a6d1f295035deb6d7c1db69a78fdec7ebdf9340d19708496f1392bb5cac997bd",
    "sha256": "0977591cf2942539f3e19b82f2175ed099750f91ee29438864f757d7536ee53d",
    "build_date": "2024-06-04T23:11:34",
    "repo_url": "https://github.com/DominicBreuker/pspy",
    "repo_author": "DominicBreuker",
    "repo_info": "Monitor linux processes without root permissions",
    "repo_updated": "2023-01-17T21:09:22Z",
    "repo_released": "2023-01-17T21:10:08Z",
    "repo_version": "v1.2.1",
    "repo_stars": "4694",
    "repo_language": "Go",
    "repo_license": "GNU General Public License v3.0",
    "repo_topics": "ctf, enumeration, golang, pentesting, privesc, security",
    "web_url": "https://github.com/DominicBreuker/pspy",
    "extra_bins": ""
  },
  {
    "name": "rclone",
    "description": "Rsync for cloud storage",
    "download_url": "https://bin.ajam.dev/arm64_v8a_Android/rclone",
    "size": "85.32 MB",
    "b3sum": "d89e781d0b4545ada8297aebe2a2ee407cb96917f54aca7ce42aaae2e35547fd",
    "sha256": "7147aefe42494841c8433b59141a359377df8fbfe1d5b099b28552c96d12bf1d",
    "build_date": "2024-06-16T23:10:29",
    "repo_url": "https://github.com/rclone/rclone",
    "repo_author": "rclone",
    "repo_info": "rsync for cloud storage - Google Drive, S3, Dropbox, Backblaze B2, One Drive, Swift, Hubic, Wasabi, Google Cloud Storage, Azure Blob, Azure Files, Yandex Files",
    "repo_updated": "2024-06-17T14:00:14Z",
    "repo_released": "2024-06-14T16:58:29Z",
    "repo_version": "v1.67.0",
    "repo_stars": "44680",
    "repo_language": "Go",
    "repo_license": "MIT License",
    "repo_topics": "azure-blob, azure-blob-storage, azure-files, backblaze-b2, cloud-storage, dropbox, encryption, ftp, fuse-filesystem, go, golang, google-cloud-storage, google-drive, onedrive, openstack-swift, rclone, s3, sftp, sync, webdav",
    "web_url": "https://github.com/rclone/rclone",
    "extra_bins": ""
  },
  {
    "name": "sudo",
    "description": "Download with resuming and segmented downloading",
    "download_url": "https://bin.ajam.dev/arm64_v8a_Android/sudo",
    "size": "250.38 kB",
    "b3sum": "261a7ec6cf5ed2fbc82f8128f2583eda7faeb8939b9e08143046f0b046e504ae",
    "sha256": "9e56787b3ca489a9eb9e3a64f54944aa92c728d18576972ef7ef6bb10ca6462c",
    "build_date": "2024-02-02T04:20:30",
    "repo_url": "https://github.com/agnostic-apollo/sudo",
    "repo_author": "agnostic-apollo",
    "repo_info": "A wrapper script to drop to the supported shells or execute shell script files or their text passed as an argument with superuser (root) context in termux",
    "repo_updated": "2021-04-10T21:03:10Z",
    "repo_released": "2021-04-10T21:03:11Z",
    "repo_version": "v0.2.0",
    "repo_stars": "80",
    "repo_language": "Shell",
    "repo_license": "MIT License",
    "repo_topics": "bash, tasker, termux, termux-tasker",
    "web_url": "https://github.com/agnostic-apollo/sudo",
    "extra_bins": ""
  },
  {
    "name": "tailscale",
    "description": "The easiest, most secure way to use WireGuard and 2FA",
    "download_url": "https://bin.ajam.dev/arm64_v8a_Android/tailscale",
    "size": "11.5 MB",
    "b3sum": "1469a06f23b00bfc84cae1fcf617d5f49789aa9f19f62bae7cc01ef68c03d3f3",
    "sha256": "5e74d8cc1e2334e879bfdce49ef5a5545540bf11d66c8b695bc241c5e9280368",
    "build_date": "2024-06-16T23:11:26",
    "repo_url": "https://github.com/tailscale/tailscale",
    "repo_author": "tailscale",
    "repo_info": "The easiest, most secure way to use WireGuard and 2FA.",
    "repo_updated": "2024-06-17T21:06:54Z",
    "repo_released": "2024-06-12T18:08:44Z",
    "repo_version": "v1.68.0",
    "repo_stars": "17260",
    "repo_language": "Go",
    "repo_license": "BSD 3-Clause New or Revised License",
    "repo_topics": "2fa, oauth, sso, tailscale, vpn, wireguard",
    "web_url": "https://github.com/tailscale/tailscale",
    "extra_bins": "tailscale_combined,tailscaled"
  },
  {
    "name": "tailscale_combined",
    "description": "The easiest, most secure way to use WireGuard and 2FA",
    "download_url": "https://bin.ajam.dev/arm64_v8a_Android/tailscale_combined",
    "size": "25.8 MB",
    "b3sum": "5268623ddaad5c82c5ca3f2af32170f6fc38a0b28735d9ce39edb85d3d47d907",
    "sha256": "e7df786394b1c1f8d87d10c4afa5337f4851a79c170e343a223b836f630739fa",
    "build_date": "2024-06-16T23:11:26",
    "repo_url": "https://github.com/tailscale/tailscale",
    "repo_author": "tailscale",
    "repo_info": "The easiest, most secure way to use WireGuard and 2FA.",
    "repo_updated": "2024-06-17T21:06:54Z",
    "repo_released": "2024-06-12T18:08:44Z",
    "repo_version": "v1.68.0",
    "repo_stars": "17260",
    "repo_language": "Go",
    "repo_license": "BSD 3-Clause New or Revised License",
    "repo_topics": "2fa, oauth, sso, tailscale, vpn, wireguard",
    "web_url": "https://github.com/tailscale/tailscale",
    "extra_bins": "tailscale,tailscaled"
  },
  {
    "name": "tailscaled",
    "description": "The easiest, most secure way to use WireGuard and 2FA",
    "download_url": "https://bin.ajam.dev/arm64_v8a_Android/tailscaled",
    "size": "23.7 MB",
    "b3sum": "bbcb456d01c78bc3b1f050be14da02f629a3864f876e481650c1ff5fb6e6d4f2",
    "sha256": "77b19e9bfa2ba02913e03d7ebcf85becfd2742ae32be6e3250e9e26176a1289d",
    "build_date": "2024-06-16T23:11:26",
    "repo_url": "https://github.com/tailscale/tailscale",
    "repo_author": "tailscale",
    "repo_info": "The easiest, most secure way to use WireGuard and 2FA.",
    "repo_updated": "2024-06-17T21:06:54Z",
    "repo_released": "2024-06-12T18:08:44Z",
    "repo_version": "v1.68.0",
    "repo_stars": "17260",
    "repo_language": "Go",
    "repo_license": "BSD 3-Clause New or Revised License",
    "repo_topics": "2fa, oauth, sso, tailscale, vpn, wireguard",
    "web_url": "https://github.com/tailscale/tailscale",
    "extra_bins": "tailscale,tailscale_combined"
  },
  {
    "name": "tmux",
    "description": "Terminal multiplexer",
    "download_url": "https://bin.ajam.dev/arm64_v8a_Android/tmux",
    "size": "1.55 MB",
    "b3sum": "ece33ecc0724c9da1f3393193b58ee5ea270fd4ddc319a9968b45a38d175615e",
    "sha256": "f60fd4ab07f6ee56815f50daecd1d4dfc57a35a7de13c4e24ce975b97b388764",
    "build_date": "2024-06-16T23:12:53",
    "repo_url": "https://github.com/tmux/tmux",
    "repo_author": "tmux",
    "repo_info": "tmux source code",
    "repo_updated": "2024-06-03T16:01:27Z",
    "repo_released": "2024-02-13T10:22:31Z",
    "repo_version": "3.4",
    "repo_stars": "33577",
    "repo_language": "C",
    "repo_license": "Other",
    "repo_topics": "",
    "web_url": "https://github.com/tmux/tmux",
    "extra_bins": ""
  },
  {
    "name": "vim",
    "description": "Vi IMproved - enhanced vi editor",
    "download_url": "https://bin.ajam.dev/arm64_v8a_Android/vim",
    "size": "5.06 MB",
    "b3sum": "93c38d4644169322939e6a8e777657e4104681d1cfbabd48eaa489771db2d7de",
    "sha256": "468a972150c5a45630dc619f022a2e5de470667d1e53aa095aaffc13fb98b300",
    "build_date": "2024-06-16T23:23:25",
    "repo_url": "https://github.com/vim/vim",
    "repo_author": "vim",
    "repo_info": "The official Vim repository",
    "repo_updated": "2024-06-17T20:54:30Z",
    "repo_released": "",
    "repo_version": "v9.1.0496",
    "repo_stars": "35386",
    "repo_language": "Vim Script",
    "repo_license": "Vim License",
    "repo_topics": "c, cross-platform, text-editor, vim",
    "web_url": "https://github.com/vim/vim",
    "extra_bins": ""
  },
  {
    "name": "wget",
    "description": "Tool for retrieving files using HTTP, HTTPS, and FTP",
    "download_url": "https://bin.ajam.dev/arm64_v8a_Android/wget",
    "size": "5.81 MB",
    "b3sum": "d46f5c4c1070310e467f2efc896323a0ddc240b81c3acc5e4af3f7ef6967c74b",
    "sha256": "326130f2f003321210a33d57e7bb03f2840f835be490f6b3f80d6fae5ffdea4e",
    "build_date": "2024-06-16T23:24:29",
    "repo_url": "",
    "web_url": "https://www.gnu.org/software/wget/",
    "extra_bins": "wget_cacert.pem"
  },
  {
    "name": "wget_cacert.pem",
    "description": "Tool for retrieving files using HTTP, HTTPS, and FTP",
    "download_url": "https://bin.ajam.dev/arm64_v8a_Android/wget_cacert.pem",
    "size": "229.65 kB",
    "b3sum": "b58055305c0fb5874b11a4e49ba49356674d8ce927aaea6ffa2632d7f4a53653",
    "sha256": "1794c1d4f7055b7d02c2170337b61b48a2ef6c90d77e95444fd2596f4cac609f",
    "build_date": "2024-05-07T08:06:47",
    "repo_url": "",
    "web_url": "https://www.gnu.org/software/wget/",
    "extra_bins": "wget"
  },
  {
    "name": "zsh",
    "description": "Z Shell",
    "download_url": "https://bin.ajam.dev/arm64_v8a_Android/zsh",
    "size": "1.8 MB",
    "b3sum": "9b2ca606e91e78de3271d52dbe7cd9065ad889bbc240db2ebb9a8fa465d6553f",
    "sha256": "1b60ee08012eab5a197c25ef7e0582ea3580abaf30ba28719c584b44cfadf397",
    "build_date": "2024-06-16T23:26:06",
    "repo_url": "https://github.com/zsh-users/zsh",
    "repo_author": "zsh-users",
    "repo_info": "Mirror of the Z shell source code repository.",
    "repo_updated": "2024-06-13T02:41:37Z",
    "repo_released": "",
    "repo_version": "zsh-5.9",
    "repo_stars": "3515",
    "repo_language": "C",
    "repo_license": "Other",
    "repo_topics": "",
    "web_url": "https://github.com/zsh-users/zsh",
    "extra_bins": ""
  }
]
